{
  "slug": "bitcoin-up-or-down-december-7-4am-et",
  "wallet": "0x6031b6eed1c97e853c6e0f03ad3ce3529351f96d",
  "exported_at": "2025-12-23T12:35:41.409887",
  "summary": {
    "resolution": "NO",
    "total_trades": 118,
    "time_range": {
      "first_trade": "2025-12-07 06:00:31",
      "last_trade": "2025-12-07 06:44:35",
      "first_trade_ts": 1765098031,
      "last_trade_ts": 1765100675
    },
    "final_position": {
      "remaining_yes_shares": 895.79,
      "remaining_no_shares": 725.86
    },
    "costs": {
      "yes_buy_shares": 895.79,
      "yes_buy_cost": 318.6317,
      "yes_sell_shares": 0,
      "yes_sell_cost": 0,
      "no_buy_shares": 725.86,
      "no_buy_cost": 382.7431,
      "no_sell_shares": 0,
      "no_sell_cost": 0
    },
    "pnl": {
      "total_spent": 701.3748,
      "final_value": 725.86,
      "pnl": 24.4852,
      "pnl_percent": 3.49
    }
  },
  "trades": [
    {
      "trade_number": 1,
      "timestamp": 1765098031,
      "datetime": "2025-12-07 06:00:31",
      "action": "BUY",
      "outcome": "YES",
      "price": 0.46,
      "price_cents": 46.0,
      "shares": 16.0,
      "cost_usd": 7.36,
      "transaction_hash": "0x0ba3f54c3d221a805f3d5863f5fc5b24ec2f2acdb18cfbfcb38280a8a19c593e",
      "running_yes_shares": 16.0,
      "running_no_shares": 0,
      "running_yes_cost": 7.36,
      "running_no_cost": 0,
      "running_total_exposure": 7.36,
      "raw": {
        "proxyWallet": "0x6031b6eed1c97e853c6e0f03ad3ce3529351f96d",
        "asset": "91528401740238005717802973551490004353166851233063526555597421997428947532492",
        "conditionId": "0x920d65638f8b944418e35a41af586cbb01dbbd458dff1ce69a0291c6ef537e89",
        "outcomeIndex": 0
      }
    },
    {
      "trade_number": 2,
      "timestamp": 1765098031,
      "datetime": "2025-12-07 06:00:31",
      "action": "BUY",
      "outcome": "YES",
      "price": 0.48,
      "price_cents": 48.0,
      "shares": 16.0,
      "cost_usd": 7.68,
      "transaction_hash": "0xdc59226fe8590e07db19e5a8c3446314c70c93970608baf357d9ca3ca8b77749",
      "running_yes_shares": 32.0,
      "running_no_shares": 0,
      "running_yes_cost": 15.04,
      "running_no_cost": 0,
      "running_total_exposure": 15.04,
      "raw": {
        "proxyWallet": "0x6031b6eed1c97e853c6e0f03ad3ce3529351f96d",
        "asset": "91528401740238005717802973551490004353166851233063526555597421997428947532492",
        "conditionId": "0x920d65638f8b944418e35a41af586cbb01dbbd458dff1ce69a0291c6ef537e89",
        "outcomeIndex": 0
      }
    },
    {
      "trade_number": 3,
      "timestamp": 1765098033,
      "datetime": "2025-12-07 06:00:33",
      "action": "BUY",
      "outcome": "YES",
      "price": 0.49,
      "price_cents": 49.0,
      "shares": 16.0,
      "cost_usd": 7.84,
      "transaction_hash": "0x9ddff291820efd8e9a8346c72eb62a89573b7ae712fc8b0dabee41f7b22cc713",
      "running_yes_shares": 48.0,
      "running_no_shares": 0,
      "running_yes_cost": 22.88,
      "running_no_cost": 0,
      "running_total_exposure": 22.88,
      "raw": {
        "proxyWallet": "0x6031b6eed1c97e853c6e0f03ad3ce3529351f96d",
        "asset": "91528401740238005717802973551490004353166851233063526555597421997428947532492",
        "conditionId": "0x920d65638f8b944418e35a41af586cbb01dbbd458dff1ce69a0291c6ef537e89",
        "outcomeIndex": 0
      }
    },
    {
      "trade_number": 4,
      "timestamp": 1765098033,
      "datetime": "2025-12-07 06:00:33",
      "action": "BUY",
      "outcome": "YES",
      "price": 0.46,
      "price_cents": 46.0,
      "shares": 16.0,
      "cost_usd": 7.36,
      "transaction_hash": "0x9e92a6ab2616620ad0d1b278480c34129bc6ee9a2e16955a6bec59c6d6327da0",
      "running_yes_shares": 64.0,
      "running_no_shares": 0,
      "running_yes_cost": 30.24,
      "running_no_cost": 0,
      "running_total_exposure": 30.24,
      "raw": {
        "proxyWallet": "0x6031b6eed1c97e853c6e0f03ad3ce3529351f96d",
        "asset": "91528401740238005717802973551490004353166851233063526555597421997428947532492",
        "conditionId": "0x920d65638f8b944418e35a41af586cbb01dbbd458dff1ce69a0291c6ef537e89",
        "outcomeIndex": 0
      }
    },
    {
      "trade_number": 5,
      "timestamp": 1765098033,
      "datetime": "2025-12-07 06:00:33",
      "action": "BUY",
      "outcome": "YES",
      "price": 0.46,
      "price_cents": 46.0,
      "shares": 16.0,
      "cost_usd": 7.36,
      "transaction_hash": "0x868806382ae717bbc54e4d88bbd032864ca81192699a2edfd08b58febee5610e",
      "running_yes_shares": 80.0,
      "running_no_shares": 0,
      "running_yes_cost": 37.6,
      "running_no_cost": 0,
      "running_total_exposure": 37.6,
      "raw": {
        "proxyWallet": "0x6031b6eed1c97e853c6e0f03ad3ce3529351f96d",
        "asset": "91528401740238005717802973551490004353166851233063526555597421997428947532492",
        "conditionId": "0x920d65638f8b944418e35a41af586cbb01dbbd458dff1ce69a0291c6ef537e89",
        "outcomeIndex": 0
      }
    },
    {
      "trade_number": 6,
      "timestamp": 1765098059,
      "datetime": "2025-12-07 06:00:59",
      "action": "BUY",
      "outcome": "YES",
      "price": 0.51,
      "price_cents": 51.0,
      "shares": 16.0,
      "cost_usd": 8.16,
      "transaction_hash": "0x64f2e55bce5a234cb492cc03dd6a51653fd1d4302753d0f9973105100670ea54",
      "running_yes_shares": 96.0,
      "running_no_shares": 0,
      "running_yes_cost": 45.76,
      "running_no_cost": 0,
      "running_total_exposure": 45.76,
      "raw": {
        "proxyWallet": "0x6031b6eed1c97e853c6e0f03ad3ce3529351f96d",
        "asset": "91528401740238005717802973551490004353166851233063526555597421997428947532492",
        "conditionId": "0x920d65638f8b944418e35a41af586cbb01dbbd458dff1ce69a0291c6ef537e89",
        "outcomeIndex": 0
      }
    },
    {
      "trade_number": 7,
      "timestamp": 1765098061,
      "datetime": "2025-12-07 06:01:01",
      "action": "BUY",
      "outcome": "YES",
      "price": 0.52,
      "price_cents": 52.0,
      "shares": 7.1,
      "cost_usd": 3.692,
      "transaction_hash": "0x43dd9aace4b9cbac781c0539cff6481f41af19e5cc562579ace72e4f1b05ad36",
      "running_yes_shares": 103.1,
      "running_no_shares": 0,
      "running_yes_cost": 49.452,
      "running_no_cost": 0,
      "running_total_exposure": 49.452,
      "raw": {
        "proxyWallet": "0x6031b6eed1c97e853c6e0f03ad3ce3529351f96d",
        "asset": "91528401740238005717802973551490004353166851233063526555597421997428947532492",
        "conditionId": "0x920d65638f8b944418e35a41af586cbb01dbbd458dff1ce69a0291c6ef537e89",
        "outcomeIndex": 0
      }
    },
    {
      "trade_number": 8,
      "timestamp": 1765098071,
      "datetime": "2025-12-07 06:01:11",
      "action": "BUY",
      "outcome": "NO",
      "price": 0.46,
      "price_cents": 46.0,
      "shares": 16.0,
      "cost_usd": 7.36,
      "transaction_hash": "0x1c543f11549810f2a53d621ffbebcf41bb5b6336e20b2c052aa78ebb2033ea8a",
      "running_yes_shares": 103.1,
      "running_no_shares": 16.0,
      "running_yes_cost": 49.452,
      "running_no_cost": 7.36,
      "running_total_exposure": 56.812,
      "raw": {
        "proxyWallet": "0x6031b6eed1c97e853c6e0f03ad3ce3529351f96d",
        "asset": "24171791432867916848656083222804673305751745875361756606303355044034777352842",
        "conditionId": "0x920d65638f8b944418e35a41af586cbb01dbbd458dff1ce69a0291c6ef537e89",
        "outcomeIndex": 1
      }
    },
    {
      "trade_number": 9,
      "timestamp": 1765098071,
      "datetime": "2025-12-07 06:01:11",
      "action": "BUY",
      "outcome": "NO",
      "price": 0.46,
      "price_cents": 46.0,
      "shares": 16.0,
      "cost_usd": 7.36,
      "transaction_hash": "0x84b3e34b8514a9767d7cef607876aecf6deeab4d04ae3f802b4dfd46c6998ac3",
      "running_yes_shares": 103.1,
      "running_no_shares": 32.0,
      "running_yes_cost": 49.452,
      "running_no_cost": 14.72,
      "running_total_exposure": 64.172,
      "raw": {
        "proxyWallet": "0x6031b6eed1c97e853c6e0f03ad3ce3529351f96d",
        "asset": "24171791432867916848656083222804673305751745875361756606303355044034777352842",
        "conditionId": "0x920d65638f8b944418e35a41af586cbb01dbbd458dff1ce69a0291c6ef537e89",
        "outcomeIndex": 1
      }
    },
    {
      "trade_number": 10,
      "timestamp": 1765098073,
      "datetime": "2025-12-07 06:01:13",
      "action": "BUY",
      "outcome": "NO",
      "price": 0.46,
      "price_cents": 46.0,
      "shares": 16.0,
      "cost_usd": 7.36,
      "transaction_hash": "0x9668ba472e6d2caee5537cb004259f0b477a7f71038134dc76e7dc7feb5c2c5f",
      "running_yes_shares": 103.1,
      "running_no_shares": 48.0,
      "running_yes_cost": 49.452,
      "running_no_cost": 22.08,
      "running_total_exposure": 71.532,
      "raw": {
        "proxyWallet": "0x6031b6eed1c97e853c6e0f03ad3ce3529351f96d",
        "asset": "24171791432867916848656083222804673305751745875361756606303355044034777352842",
        "conditionId": "0x920d65638f8b944418e35a41af586cbb01dbbd458dff1ce69a0291c6ef537e89",
        "outcomeIndex": 1
      }
    },
    {
      "trade_number": 11,
      "timestamp": 1765098077,
      "datetime": "2025-12-07 06:01:17",
      "action": "BUY",
      "outcome": "YES",
      "price": 0.55,
      "price_cents": 55.0,
      "shares": 16.0,
      "cost_usd": 8.8,
      "transaction_hash": "0xf6d90fb04785dbca7112b0c4dc43c5b4e92c13c40c406a852db32f53d48ff625",
      "running_yes_shares": 119.1,
      "running_no_shares": 48.0,
      "running_yes_cost": 58.252,
      "running_no_cost": 22.08,
      "running_total_exposure": 80.332,
      "raw": {
        "proxyWallet": "0x6031b6eed1c97e853c6e0f03ad3ce3529351f96d",
        "asset": "91528401740238005717802973551490004353166851233063526555597421997428947532492",
        "conditionId": "0x920d65638f8b944418e35a41af586cbb01dbbd458dff1ce69a0291c6ef537e89",
        "outcomeIndex": 0
      }
    },
    {
      "trade_number": 12,
      "timestamp": 1765098131,
      "datetime": "2025-12-07 06:02:11",
      "action": "BUY",
      "outcome": "NO",
      "price": 0.45,
      "price_cents": 45.0,
      "shares": 16.0,
      "cost_usd": 7.2,
      "transaction_hash": "0xa1cbc1dff02b88714df602f1fb6d5a0cfaf8ef689335091ab3499f624502edc4",
      "running_yes_shares": 119.1,
      "running_no_shares": 64.0,
      "running_yes_cost": 58.252,
      "running_no_cost": 29.28,
      "running_total_exposure": 87.532,
      "raw": {
        "proxyWallet": "0x6031b6eed1c97e853c6e0f03ad3ce3529351f96d",
        "asset": "24171791432867916848656083222804673305751745875361756606303355044034777352842",
        "conditionId": "0x920d65638f8b944418e35a41af586cbb01dbbd458dff1ce69a0291c6ef537e89",
        "outcomeIndex": 1
      }
    },
    {
      "trade_number": 13,
      "timestamp": 1765098131,
      "datetime": "2025-12-07 06:02:11",
      "action": "BUY",
      "outcome": "NO",
      "price": 0.45,
      "price_cents": 45.0,
      "shares": 6.0,
      "cost_usd": 2.7,
      "transaction_hash": "0x5d0eb4a035c36f816909dd55b39c577f538dffdedebabe3219fc79a8c3da3926",
      "running_yes_shares": 119.1,
      "running_no_shares": 70.0,
      "running_yes_cost": 58.252,
      "running_no_cost": 31.98,
      "running_total_exposure": 90.232,
      "raw": {
        "proxyWallet": "0x6031b6eed1c97e853c6e0f03ad3ce3529351f96d",
        "asset": "24171791432867916848656083222804673305751745875361756606303355044034777352842",
        "conditionId": "0x920d65638f8b944418e35a41af586cbb01dbbd458dff1ce69a0291c6ef537e89",
        "outcomeIndex": 1
      }
    },
    {
      "trade_number": 14,
      "timestamp": 1765098233,
      "datetime": "2025-12-07 06:03:53",
      "action": "BUY",
      "outcome": "NO",
      "price": 0.34,
      "price_cents": 34.0,
      "shares": 16.0,
      "cost_usd": 5.44,
      "transaction_hash": "0x94b501c8340730ce464a5a6266bec0e3a91835113d2acca5e5c75372a2b213ac",
      "running_yes_shares": 119.1,
      "running_no_shares": 86.0,
      "running_yes_cost": 58.252,
      "running_no_cost": 37.42,
      "running_total_exposure": 95.672,
      "raw": {
        "proxyWallet": "0x6031b6eed1c97e853c6e0f03ad3ce3529351f96d",
        "asset": "24171791432867916848656083222804673305751745875361756606303355044034777352842",
        "conditionId": "0x920d65638f8b944418e35a41af586cbb01dbbd458dff1ce69a0291c6ef537e89",
        "outcomeIndex": 1
      }
    },
    {
      "trade_number": 15,
      "timestamp": 1765098233,
      "datetime": "2025-12-07 06:03:53",
      "action": "BUY",
      "outcome": "NO",
      "price": 0.34,
      "price_cents": 34.0,
      "shares": 16.0,
      "cost_usd": 5.44,
      "transaction_hash": "0x03a7a581934e17bd2659caf2a3951f9bc12949b02d0a06987f8adc87fbf35437",
      "running_yes_shares": 119.1,
      "running_no_shares": 102.0,
      "running_yes_cost": 58.252,
      "running_no_cost": 42.86,
      "running_total_exposure": 101.112,
      "raw": {
        "proxyWallet": "0x6031b6eed1c97e853c6e0f03ad3ce3529351f96d",
        "asset": "24171791432867916848656083222804673305751745875361756606303355044034777352842",
        "conditionId": "0x920d65638f8b944418e35a41af586cbb01dbbd458dff1ce69a0291c6ef537e89",
        "outcomeIndex": 1
      }
    },
    {
      "trade_number": 16,
      "timestamp": 1765098233,
      "datetime": "2025-12-07 06:03:53",
      "action": "BUY",
      "outcome": "NO",
      "price": 0.34,
      "price_cents": 34.0,
      "shares": 16.0,
      "cost_usd": 5.44,
      "transaction_hash": "0xddbfc7ee0b6ffcb7c2536308398a09ca4cb0b5a2c190b3838286e7c9f32b201f",
      "running_yes_shares": 119.1,
      "running_no_shares": 118.0,
      "running_yes_cost": 58.252,
      "running_no_cost": 48.3,
      "running_total_exposure": 106.552,
      "raw": {
        "proxyWallet": "0x6031b6eed1c97e853c6e0f03ad3ce3529351f96d",
        "asset": "24171791432867916848656083222804673305751745875361756606303355044034777352842",
        "conditionId": "0x920d65638f8b944418e35a41af586cbb01dbbd458dff1ce69a0291c6ef537e89",
        "outcomeIndex": 1
      }
    },
    {
      "trade_number": 17,
      "timestamp": 1765098233,
      "datetime": "2025-12-07 06:03:53",
      "action": "BUY",
      "outcome": "NO",
      "price": 0.34,
      "price_cents": 34.0,
      "shares": 16.0,
      "cost_usd": 5.44,
      "transaction_hash": "0x9a0c4925c2393dace31063a7e94e1090ff9a330936d373281986805345ebe448",
      "running_yes_shares": 119.1,
      "running_no_shares": 134.0,
      "running_yes_cost": 58.252,
      "running_no_cost": 53.74,
      "running_total_exposure": 111.992,
      "raw": {
        "proxyWallet": "0x6031b6eed1c97e853c6e0f03ad3ce3529351f96d",
        "asset": "24171791432867916848656083222804673305751745875361756606303355044034777352842",
        "conditionId": "0x920d65638f8b944418e35a41af586cbb01dbbd458dff1ce69a0291c6ef537e89",
        "outcomeIndex": 1
      }
    },
    {
      "trade_number": 18,
      "timestamp": 1765098233,
      "datetime": "2025-12-07 06:03:53",
      "action": "BUY",
      "outcome": "NO",
      "price": 0.34,
      "price_cents": 34.0,
      "shares": 16.0,
      "cost_usd": 5.44,
      "transaction_hash": "0x4e612a11735876dde0b1333e33fdccf6299602539a1741c139f53580e78f2d9e",
      "running_yes_shares": 119.1,
      "running_no_shares": 150.0,
      "running_yes_cost": 58.252,
      "running_no_cost": 59.18,
      "running_total_exposure": 117.432,
      "raw": {
        "proxyWallet": "0x6031b6eed1c97e853c6e0f03ad3ce3529351f96d",
        "asset": "24171791432867916848656083222804673305751745875361756606303355044034777352842",
        "conditionId": "0x920d65638f8b944418e35a41af586cbb01dbbd458dff1ce69a0291c6ef537e89",
        "outcomeIndex": 1
      }
    },
    {
      "trade_number": 19,
      "timestamp": 1765098403,
      "datetime": "2025-12-07 06:06:43",
      "action": "BUY",
      "outcome": "NO",
      "price": 0.4,
      "price_cents": 40.0,
      "shares": 16.0,
      "cost_usd": 6.4,
      "transaction_hash": "0x8bc7edb521a9048618070dac8d46c315877c4107f030874712894cdf5d75e78b",
      "running_yes_shares": 119.1,
      "running_no_shares": 166.0,
      "running_yes_cost": 58.252,
      "running_no_cost": 65.58,
      "running_total_exposure": 123.832,
      "raw": {
        "proxyWallet": "0x6031b6eed1c97e853c6e0f03ad3ce3529351f96d",
        "asset": "24171791432867916848656083222804673305751745875361756606303355044034777352842",
        "conditionId": "0x920d65638f8b944418e35a41af586cbb01dbbd458dff1ce69a0291c6ef537e89",
        "outcomeIndex": 1
      }
    },
    {
      "trade_number": 20,
      "timestamp": 1765098403,
      "datetime": "2025-12-07 06:06:43",
      "action": "BUY",
      "outcome": "NO",
      "price": 0.4,
      "price_cents": 40.0,
      "shares": 16.0,
      "cost_usd": 6.4,
      "transaction_hash": "0xb69285d463a04d65a13eb4cecf88fe340fd2ab4cb2528e990693de635bc6d161",
      "running_yes_shares": 119.1,
      "running_no_shares": 182.0,
      "running_yes_cost": 58.252,
      "running_no_cost": 71.98,
      "running_total_exposure": 130.232,
      "raw": {
        "proxyWallet": "0x6031b6eed1c97e853c6e0f03ad3ce3529351f96d",
        "asset": "24171791432867916848656083222804673305751745875361756606303355044034777352842",
        "conditionId": "0x920d65638f8b944418e35a41af586cbb01dbbd458dff1ce69a0291c6ef537e89",
        "outcomeIndex": 1
      }
    },
    {
      "trade_number": 21,
      "timestamp": 1765098403,
      "datetime": "2025-12-07 06:06:43",
      "action": "BUY",
      "outcome": "NO",
      "price": 0.4,
      "price_cents": 40.0,
      "shares": 16.0,
      "cost_usd": 6.4,
      "transaction_hash": "0xd2c1f6da0f79f4b99a88586fd4e4dc072da4bb7af93fd476450e6cbd467c453a",
      "running_yes_shares": 119.1,
      "running_no_shares": 198.0,
      "running_yes_cost": 58.252,
      "running_no_cost": 78.38,
      "running_total_exposure": 136.632,
      "raw": {
        "proxyWallet": "0x6031b6eed1c97e853c6e0f03ad3ce3529351f96d",
        "asset": "24171791432867916848656083222804673305751745875361756606303355044034777352842",
        "conditionId": "0x920d65638f8b944418e35a41af586cbb01dbbd458dff1ce69a0291c6ef537e89",
        "outcomeIndex": 1
      }
    },
    {
      "trade_number": 22,
      "timestamp": 1765098403,
      "datetime": "2025-12-07 06:06:43",
      "action": "BUY",
      "outcome": "NO",
      "price": 0.4,
      "price_cents": 40.0,
      "shares": 16.0,
      "cost_usd": 6.4,
      "transaction_hash": "0x921d1750e7a0d7cc781e601663135056caf20dbf334922c588c1c6d7454dec15",
      "running_yes_shares": 119.1,
      "running_no_shares": 214.0,
      "running_yes_cost": 58.252,
      "running_no_cost": 84.78,
      "running_total_exposure": 143.032,
      "raw": {
        "proxyWallet": "0x6031b6eed1c97e853c6e0f03ad3ce3529351f96d",
        "asset": "24171791432867916848656083222804673305751745875361756606303355044034777352842",
        "conditionId": "0x920d65638f8b944418e35a41af586cbb01dbbd458dff1ce69a0291c6ef537e89",
        "outcomeIndex": 1
      }
    },
    {
      "trade_number": 23,
      "timestamp": 1765098403,
      "datetime": "2025-12-07 06:06:43",
      "action": "BUY",
      "outcome": "NO",
      "price": 0.4,
      "price_cents": 40.0,
      "shares": 16.0,
      "cost_usd": 6.4,
      "transaction_hash": "0xec75b6a6a74dfeb419ee8ac76be3553de449337c0c1ecbcd56557134b7c048a2",
      "running_yes_shares": 119.1,
      "running_no_shares": 230.0,
      "running_yes_cost": 58.252,
      "running_no_cost": 91.18,
      "running_total_exposure": 149.432,
      "raw": {
        "proxyWallet": "0x6031b6eed1c97e853c6e0f03ad3ce3529351f96d",
        "asset": "24171791432867916848656083222804673305751745875361756606303355044034777352842",
        "conditionId": "0x920d65638f8b944418e35a41af586cbb01dbbd458dff1ce69a0291c6ef537e89",
        "outcomeIndex": 1
      }
    },
    {
      "trade_number": 24,
      "timestamp": 1765098423,
      "datetime": "2025-12-07 06:07:03",
      "action": "BUY",
      "outcome": "YES",
      "price": 0.61,
      "price_cents": 61.0,
      "shares": 16.0,
      "cost_usd": 9.76,
      "transaction_hash": "0xe33a960c84a4f795af6e3133fbb5ac6472f5d780a4fa584955d6db81a8a4613b",
      "running_yes_shares": 135.1,
      "running_no_shares": 230.0,
      "running_yes_cost": 68.012,
      "running_no_cost": 91.18,
      "running_total_exposure": 159.192,
      "raw": {
        "proxyWallet": "0x6031b6eed1c97e853c6e0f03ad3ce3529351f96d",
        "asset": "91528401740238005717802973551490004353166851233063526555597421997428947532492",
        "conditionId": "0x920d65638f8b944418e35a41af586cbb01dbbd458dff1ce69a0291c6ef537e89",
        "outcomeIndex": 0
      }
    },
    {
      "trade_number": 25,
      "timestamp": 1765098423,
      "datetime": "2025-12-07 06:07:03",
      "action": "BUY",
      "outcome": "YES",
      "price": 0.61,
      "price_cents": 61.0,
      "shares": 16.0,
      "cost_usd": 9.76,
      "transaction_hash": "0x24ca764749a165c7b3ae20eb213f10761c96a11937a129c4fc721c2026d03a88",
      "running_yes_shares": 151.1,
      "running_no_shares": 230.0,
      "running_yes_cost": 77.772,
      "running_no_cost": 91.18,
      "running_total_exposure": 168.952,
      "raw": {
        "proxyWallet": "0x6031b6eed1c97e853c6e0f03ad3ce3529351f96d",
        "asset": "91528401740238005717802973551490004353166851233063526555597421997428947532492",
        "conditionId": "0x920d65638f8b944418e35a41af586cbb01dbbd458dff1ce69a0291c6ef537e89",
        "outcomeIndex": 0
      }
    },
    {
      "trade_number": 26,
      "timestamp": 1765098423,
      "datetime": "2025-12-07 06:07:03",
      "action": "BUY",
      "outcome": "YES",
      "price": 0.61,
      "price_cents": 61.0,
      "shares": 16.0,
      "cost_usd": 9.76,
      "transaction_hash": "0x3b87c383389a959e1a7107c9b9c11eef87aa018153aef85471abcadf556b05fc",
      "running_yes_shares": 167.1,
      "running_no_shares": 230.0,
      "running_yes_cost": 87.532,
      "running_no_cost": 91.18,
      "running_total_exposure": 178.712,
      "raw": {
        "proxyWallet": "0x6031b6eed1c97e853c6e0f03ad3ce3529351f96d",
        "asset": "91528401740238005717802973551490004353166851233063526555597421997428947532492",
        "conditionId": "0x920d65638f8b944418e35a41af586cbb01dbbd458dff1ce69a0291c6ef537e89",
        "outcomeIndex": 0
      }
    },
    {
      "trade_number": 27,
      "timestamp": 1765098423,
      "datetime": "2025-12-07 06:07:03",
      "action": "BUY",
      "outcome": "YES",
      "price": 0.61,
      "price_cents": 61.0,
      "shares": 16.0,
      "cost_usd": 9.76,
      "transaction_hash": "0xbcb15f17cd446985a5e2ac6a4c3bfebe3012c8c76ddfea976c0771aad7cfa4f4",
      "running_yes_shares": 183.1,
      "running_no_shares": 230.0,
      "running_yes_cost": 97.292,
      "running_no_cost": 91.18,
      "running_total_exposure": 188.472,
      "raw": {
        "proxyWallet": "0x6031b6eed1c97e853c6e0f03ad3ce3529351f96d",
        "asset": "91528401740238005717802973551490004353166851233063526555597421997428947532492",
        "conditionId": "0x920d65638f8b944418e35a41af586cbb01dbbd458dff1ce69a0291c6ef537e89",
        "outcomeIndex": 0
      }
    },
    {
      "trade_number": 28,
      "timestamp": 1765098423,
      "datetime": "2025-12-07 06:07:03",
      "action": "BUY",
      "outcome": "YES",
      "price": 0.61,
      "price_cents": 61.0,
      "shares": 16.0,
      "cost_usd": 9.76,
      "transaction_hash": "0x0375616083c59db7ecf7133d1a242b12aac00854ad1758e56d88b2e57830b7ff",
      "running_yes_shares": 199.1,
      "running_no_shares": 230.0,
      "running_yes_cost": 107.052,
      "running_no_cost": 91.18,
      "running_total_exposure": 198.232,
      "raw": {
        "proxyWallet": "0x6031b6eed1c97e853c6e0f03ad3ce3529351f96d",
        "asset": "91528401740238005717802973551490004353166851233063526555597421997428947532492",
        "conditionId": "0x920d65638f8b944418e35a41af586cbb01dbbd458dff1ce69a0291c6ef537e89",
        "outcomeIndex": 0
      }
    },
    {
      "trade_number": 29,
      "timestamp": 1765098457,
      "datetime": "2025-12-07 06:07:37",
      "action": "BUY",
      "outcome": "NO",
      "price": 0.41,
      "price_cents": 41.0,
      "shares": 16.0,
      "cost_usd": 6.56,
      "transaction_hash": "0xbd2106b737c30dff0d233c1be3f9879c677896508a2cdfe3c774a45acf4f1003",
      "running_yes_shares": 199.1,
      "running_no_shares": 246.0,
      "running_yes_cost": 107.052,
      "running_no_cost": 97.74,
      "running_total_exposure": 204.792,
      "raw": {
        "proxyWallet": "0x6031b6eed1c97e853c6e0f03ad3ce3529351f96d",
        "asset": "24171791432867916848656083222804673305751745875361756606303355044034777352842",
        "conditionId": "0x920d65638f8b944418e35a41af586cbb01dbbd458dff1ce69a0291c6ef537e89",
        "outcomeIndex": 1
      }
    },
    {
      "trade_number": 30,
      "timestamp": 1765098457,
      "datetime": "2025-12-07 06:07:37",
      "action": "BUY",
      "outcome": "NO",
      "price": 0.41,
      "price_cents": 41.0,
      "shares": 16.0,
      "cost_usd": 6.56,
      "transaction_hash": "0x7be83c71c18cb19a5947cb22f639c292acdb0fdfce0195abff44a95df1d3c48b",
      "running_yes_shares": 199.1,
      "running_no_shares": 262.0,
      "running_yes_cost": 107.052,
      "running_no_cost": 104.3,
      "running_total_exposure": 211.352,
      "raw": {
        "proxyWallet": "0x6031b6eed1c97e853c6e0f03ad3ce3529351f96d",
        "asset": "24171791432867916848656083222804673305751745875361756606303355044034777352842",
        "conditionId": "0x920d65638f8b944418e35a41af586cbb01dbbd458dff1ce69a0291c6ef537e89",
        "outcomeIndex": 1
      }
    },
    {
      "trade_number": 31,
      "timestamp": 1765098457,
      "datetime": "2025-12-07 06:07:37",
      "action": "BUY",
      "outcome": "NO",
      "price": 0.41,
      "price_cents": 41.0,
      "shares": 16.0,
      "cost_usd": 6.56,
      "transaction_hash": "0x2bf32c2fcdd75003493b1f9c93cdf2820746f6dd1880f7ef602eedf1f279c08f",
      "running_yes_shares": 199.1,
      "running_no_shares": 278.0,
      "running_yes_cost": 107.052,
      "running_no_cost": 110.86,
      "running_total_exposure": 217.912,
      "raw": {
        "proxyWallet": "0x6031b6eed1c97e853c6e0f03ad3ce3529351f96d",
        "asset": "24171791432867916848656083222804673305751745875361756606303355044034777352842",
        "conditionId": "0x920d65638f8b944418e35a41af586cbb01dbbd458dff1ce69a0291c6ef537e89",
        "outcomeIndex": 1
      }
    },
    {
      "trade_number": 32,
      "timestamp": 1765098523,
      "datetime": "2025-12-07 06:08:43",
      "action": "BUY",
      "outcome": "YES",
      "price": 0.66,
      "price_cents": 66.0,
      "shares": 5.0,
      "cost_usd": 3.3,
      "transaction_hash": "0xf2250f81243aece04cc5cc5e039247f2d8a87b3fae3ae9deaab7d49afb772216",
      "running_yes_shares": 204.1,
      "running_no_shares": 278.0,
      "running_yes_cost": 110.352,
      "running_no_cost": 110.86,
      "running_total_exposure": 221.212,
      "raw": {
        "proxyWallet": "0x6031b6eed1c97e853c6e0f03ad3ce3529351f96d",
        "asset": "91528401740238005717802973551490004353166851233063526555597421997428947532492",
        "conditionId": "0x920d65638f8b944418e35a41af586cbb01dbbd458dff1ce69a0291c6ef537e89",
        "outcomeIndex": 0
      }
    },
    {
      "trade_number": 33,
      "timestamp": 1765098559,
      "datetime": "2025-12-07 06:09:19",
      "action": "BUY",
      "outcome": "YES",
      "price": 0.64,
      "price_cents": 64.0,
      "shares": 5.0,
      "cost_usd": 3.2,
      "transaction_hash": "0x6ebda8623b3d5ecbc9e5fb63157f71977b86a4b1c3784352e0ed56a52ab4f12c",
      "running_yes_shares": 209.1,
      "running_no_shares": 278.0,
      "running_yes_cost": 113.552,
      "running_no_cost": 110.86,
      "running_total_exposure": 224.412,
      "raw": {
        "proxyWallet": "0x6031b6eed1c97e853c6e0f03ad3ce3529351f96d",
        "asset": "91528401740238005717802973551490004353166851233063526555597421997428947532492",
        "conditionId": "0x920d65638f8b944418e35a41af586cbb01dbbd458dff1ce69a0291c6ef537e89",
        "outcomeIndex": 0
      }
    },
    {
      "trade_number": 34,
      "timestamp": 1765098559,
      "datetime": "2025-12-07 06:09:19",
      "action": "BUY",
      "outcome": "YES",
      "price": 0.62,
      "price_cents": 62.0,
      "shares": 5.0,
      "cost_usd": 3.1,
      "transaction_hash": "0xd239bb681a9d620813a6226f8e090acbe8b187776e88184b7f33a95c00f2db1e",
      "running_yes_shares": 214.1,
      "running_no_shares": 278.0,
      "running_yes_cost": 116.652,
      "running_no_cost": 110.86,
      "running_total_exposure": 227.512,
      "raw": {
        "proxyWallet": "0x6031b6eed1c97e853c6e0f03ad3ce3529351f96d",
        "asset": "91528401740238005717802973551490004353166851233063526555597421997428947532492",
        "conditionId": "0x920d65638f8b944418e35a41af586cbb01dbbd458dff1ce69a0291c6ef537e89",
        "outcomeIndex": 0
      }
    },
    {
      "trade_number": 35,
      "timestamp": 1765098613,
      "datetime": "2025-12-07 06:10:13",
      "action": "BUY",
      "outcome": "NO",
      "price": 0.35,
      "price_cents": 35.0,
      "shares": 16.0,
      "cost_usd": 5.6,
      "transaction_hash": "0xb099e59137f4303f0aea905f8b856f9c7cd7db88104e93542f9bacdeee0c7537",
      "running_yes_shares": 214.1,
      "running_no_shares": 294.0,
      "running_yes_cost": 116.652,
      "running_no_cost": 116.46,
      "running_total_exposure": 233.112,
      "raw": {
        "proxyWallet": "0x6031b6eed1c97e853c6e0f03ad3ce3529351f96d",
        "asset": "24171791432867916848656083222804673305751745875361756606303355044034777352842",
        "conditionId": "0x920d65638f8b944418e35a41af586cbb01dbbd458dff1ce69a0291c6ef537e89",
        "outcomeIndex": 1
      }
    },
    {
      "trade_number": 36,
      "timestamp": 1765098613,
      "datetime": "2025-12-07 06:10:13",
      "action": "BUY",
      "outcome": "NO",
      "price": 0.35,
      "price_cents": 35.0,
      "shares": 16.0,
      "cost_usd": 5.6,
      "transaction_hash": "0xd3fe52aafaf0392a44ecf369649bc5b520b2b472ba8de39da791ecd6b9f0dc2c",
      "running_yes_shares": 214.1,
      "running_no_shares": 310.0,
      "running_yes_cost": 116.652,
      "running_no_cost": 122.06,
      "running_total_exposure": 238.712,
      "raw": {
        "proxyWallet": "0x6031b6eed1c97e853c6e0f03ad3ce3529351f96d",
        "asset": "24171791432867916848656083222804673305751745875361756606303355044034777352842",
        "conditionId": "0x920d65638f8b944418e35a41af586cbb01dbbd458dff1ce69a0291c6ef537e89",
        "outcomeIndex": 1
      }
    },
    {
      "trade_number": 37,
      "timestamp": 1765098613,
      "datetime": "2025-12-07 06:10:13",
      "action": "BUY",
      "outcome": "NO",
      "price": 0.3469,
      "price_cents": 34.69,
      "shares": 16.0,
      "cost_usd": 5.55,
      "transaction_hash": "0x989d87463aaa32edd56a0a961b081591f31adbf81de9573286cf6c9c46281e0a",
      "running_yes_shares": 214.1,
      "running_no_shares": 326.0,
      "running_yes_cost": 116.652,
      "running_no_cost": 127.61,
      "running_total_exposure": 244.262,
      "raw": {
        "proxyWallet": "0x6031b6eed1c97e853c6e0f03ad3ce3529351f96d",
        "asset": "24171791432867916848656083222804673305751745875361756606303355044034777352842",
        "conditionId": "0x920d65638f8b944418e35a41af586cbb01dbbd458dff1ce69a0291c6ef537e89",
        "outcomeIndex": 1
      }
    },
    {
      "trade_number": 38,
      "timestamp": 1765098661,
      "datetime": "2025-12-07 06:11:01",
      "action": "BUY",
      "outcome": "YES",
      "price": 0.61,
      "price_cents": 61.0,
      "shares": 5.0,
      "cost_usd": 3.05,
      "transaction_hash": "0x7a49b6f0d8aa0096a064ebbbbbd257316ba5659e1309d0311464398be4d4cc84",
      "running_yes_shares": 219.1,
      "running_no_shares": 326.0,
      "running_yes_cost": 119.702,
      "running_no_cost": 127.61,
      "running_total_exposure": 247.312,
      "raw": {
        "proxyWallet": "0x6031b6eed1c97e853c6e0f03ad3ce3529351f96d",
        "asset": "91528401740238005717802973551490004353166851233063526555597421997428947532492",
        "conditionId": "0x920d65638f8b944418e35a41af586cbb01dbbd458dff1ce69a0291c6ef537e89",
        "outcomeIndex": 0
      }
    },
    {
      "trade_number": 39,
      "timestamp": 1765098785,
      "datetime": "2025-12-07 06:13:05",
      "action": "BUY",
      "outcome": "NO",
      "price": 0.34,
      "price_cents": 34.0,
      "shares": 16.0,
      "cost_usd": 5.44,
      "transaction_hash": "0x273696cd828c9424b2ab408a525f957f52f4384638712781b3c34089f0bf2fda",
      "running_yes_shares": 219.1,
      "running_no_shares": 342.0,
      "running_yes_cost": 119.702,
      "running_no_cost": 133.05,
      "running_total_exposure": 252.752,
      "raw": {
        "proxyWallet": "0x6031b6eed1c97e853c6e0f03ad3ce3529351f96d",
        "asset": "24171791432867916848656083222804673305751745875361756606303355044034777352842",
        "conditionId": "0x920d65638f8b944418e35a41af586cbb01dbbd458dff1ce69a0291c6ef537e89",
        "outcomeIndex": 1
      }
    },
    {
      "trade_number": 40,
      "timestamp": 1765098991,
      "datetime": "2025-12-07 06:16:31",
      "action": "BUY",
      "outcome": "YES",
      "price": 0.66,
      "price_cents": 66.0,
      "shares": 16.0,
      "cost_usd": 10.56,
      "transaction_hash": "0x0752c0606a1628bc51709ebc7f5c96f12149b29fd8cb98a82816d0c6e749cce7",
      "running_yes_shares": 235.1,
      "running_no_shares": 342.0,
      "running_yes_cost": 130.262,
      "running_no_cost": 133.05,
      "running_total_exposure": 263.312,
      "raw": {
        "proxyWallet": "0x6031b6eed1c97e853c6e0f03ad3ce3529351f96d",
        "asset": "91528401740238005717802973551490004353166851233063526555597421997428947532492",
        "conditionId": "0x920d65638f8b944418e35a41af586cbb01dbbd458dff1ce69a0291c6ef537e89",
        "outcomeIndex": 0
      }
    },
    {
      "trade_number": 41,
      "timestamp": 1765098995,
      "datetime": "2025-12-07 06:16:35",
      "action": "BUY",
      "outcome": "NO",
      "price": 0.35,
      "price_cents": 35.0,
      "shares": 15.0,
      "cost_usd": 5.25,
      "transaction_hash": "0x0c0df2f8c277e41c3743ef73dab69dd803936eaf949730e8dd8755f7791119e1",
      "running_yes_shares": 235.1,
      "running_no_shares": 357.0,
      "running_yes_cost": 130.262,
      "running_no_cost": 138.3,
      "running_total_exposure": 268.562,
      "raw": {
        "proxyWallet": "0x6031b6eed1c97e853c6e0f03ad3ce3529351f96d",
        "asset": "24171791432867916848656083222804673305751745875361756606303355044034777352842",
        "conditionId": "0x920d65638f8b944418e35a41af586cbb01dbbd458dff1ce69a0291c6ef537e89",
        "outcomeIndex": 1
      }
    },
    {
      "trade_number": 42,
      "timestamp": 1765099149,
      "datetime": "2025-12-07 06:19:09",
      "action": "BUY",
      "outcome": "NO",
      "price": 0.37,
      "price_cents": 37.0,
      "shares": 5.0,
      "cost_usd": 1.85,
      "transaction_hash": "0xd03a62d29ad31d7e67db809252d9bae6018ae6221698b468771f41022000b8b8",
      "running_yes_shares": 235.1,
      "running_no_shares": 362.0,
      "running_yes_cost": 130.262,
      "running_no_cost": 140.15,
      "running_total_exposure": 270.412,
      "raw": {
        "proxyWallet": "0x6031b6eed1c97e853c6e0f03ad3ce3529351f96d",
        "asset": "24171791432867916848656083222804673305751745875361756606303355044034777352842",
        "conditionId": "0x920d65638f8b944418e35a41af586cbb01dbbd458dff1ce69a0291c6ef537e89",
        "outcomeIndex": 1
      }
    },
    {
      "trade_number": 43,
      "timestamp": 1765099149,
      "datetime": "2025-12-07 06:19:09",
      "action": "BUY",
      "outcome": "NO",
      "price": 0.35,
      "price_cents": 35.0,
      "shares": 5.0,
      "cost_usd": 1.75,
      "transaction_hash": "0xcc839904a5c13f0a5c22a0c38cf909a94d4ffc8c8b7958ec8ba2cd040cceaaea",
      "running_yes_shares": 235.1,
      "running_no_shares": 367.0,
      "running_yes_cost": 130.262,
      "running_no_cost": 141.9,
      "running_total_exposure": 272.162,
      "raw": {
        "proxyWallet": "0x6031b6eed1c97e853c6e0f03ad3ce3529351f96d",
        "asset": "24171791432867916848656083222804673305751745875361756606303355044034777352842",
        "conditionId": "0x920d65638f8b944418e35a41af586cbb01dbbd458dff1ce69a0291c6ef537e89",
        "outcomeIndex": 1
      }
    },
    {
      "trade_number": 44,
      "timestamp": 1765099151,
      "datetime": "2025-12-07 06:19:11",
      "action": "BUY",
      "outcome": "NO",
      "price": 0.38,
      "price_cents": 38.0,
      "shares": 5.0,
      "cost_usd": 1.9,
      "transaction_hash": "0xb225d53c2286f2cdf6b873f479f34ae17e921b76f336d4648de364f376682a9d",
      "running_yes_shares": 235.1,
      "running_no_shares": 372.0,
      "running_yes_cost": 130.262,
      "running_no_cost": 143.8,
      "running_total_exposure": 274.062,
      "raw": {
        "proxyWallet": "0x6031b6eed1c97e853c6e0f03ad3ce3529351f96d",
        "asset": "24171791432867916848656083222804673305751745875361756606303355044034777352842",
        "conditionId": "0x920d65638f8b944418e35a41af586cbb01dbbd458dff1ce69a0291c6ef537e89",
        "outcomeIndex": 1
      }
    },
    {
      "trade_number": 45,
      "timestamp": 1765099225,
      "datetime": "2025-12-07 06:20:25",
      "action": "BUY",
      "outcome": "YES",
      "price": 0.59,
      "price_cents": 59.0,
      "shares": 15.0,
      "cost_usd": 8.85,
      "transaction_hash": "0x9d34767aeb7c97a399bc6fa25624bea7b420a11ea63e1ccb97c93349a5968d5c",
      "running_yes_shares": 250.1,
      "running_no_shares": 372.0,
      "running_yes_cost": 139.112,
      "running_no_cost": 143.8,
      "running_total_exposure": 282.912,
      "raw": {
        "proxyWallet": "0x6031b6eed1c97e853c6e0f03ad3ce3529351f96d",
        "asset": "91528401740238005717802973551490004353166851233063526555597421997428947532492",
        "conditionId": "0x920d65638f8b944418e35a41af586cbb01dbbd458dff1ce69a0291c6ef537e89",
        "outcomeIndex": 0
      }
    },
    {
      "trade_number": 46,
      "timestamp": 1765099229,
      "datetime": "2025-12-07 06:20:29",
      "action": "BUY",
      "outcome": "NO",
      "price": 0.42,
      "price_cents": 42.0,
      "shares": 16.0,
      "cost_usd": 6.72,
      "transaction_hash": "0x401df84a3bf378d3c84bdff6c8fac8281b62acab0f08f7e9c7521356bff7521f",
      "running_yes_shares": 250.1,
      "running_no_shares": 388.0,
      "running_yes_cost": 139.112,
      "running_no_cost": 150.52,
      "running_total_exposure": 289.632,
      "raw": {
        "proxyWallet": "0x6031b6eed1c97e853c6e0f03ad3ce3529351f96d",
        "asset": "24171791432867916848656083222804673305751745875361756606303355044034777352842",
        "conditionId": "0x920d65638f8b944418e35a41af586cbb01dbbd458dff1ce69a0291c6ef537e89",
        "outcomeIndex": 1
      }
    },
    {
      "trade_number": 47,
      "timestamp": 1765099229,
      "datetime": "2025-12-07 06:20:29",
      "action": "BUY",
      "outcome": "NO",
      "price": 0.42,
      "price_cents": 42.0,
      "shares": 16.0,
      "cost_usd": 6.72,
      "transaction_hash": "0xc18e82ec46ba1b0357dc5081c9c6393f428d5af05b94169ec3a3774d97aa2bcd",
      "running_yes_shares": 250.1,
      "running_no_shares": 404.0,
      "running_yes_cost": 139.112,
      "running_no_cost": 157.24,
      "running_total_exposure": 296.352,
      "raw": {
        "proxyWallet": "0x6031b6eed1c97e853c6e0f03ad3ce3529351f96d",
        "asset": "24171791432867916848656083222804673305751745875361756606303355044034777352842",
        "conditionId": "0x920d65638f8b944418e35a41af586cbb01dbbd458dff1ce69a0291c6ef537e89",
        "outcomeIndex": 1
      }
    },
    {
      "trade_number": 48,
      "timestamp": 1765099245,
      "datetime": "2025-12-07 06:20:45",
      "action": "BUY",
      "outcome": "YES",
      "price": 0.54,
      "price_cents": 54.0,
      "shares": 16.0,
      "cost_usd": 8.64,
      "transaction_hash": "0xf8c961fa53583fb4e1ae07c900a924d39c9692789330225252fbe135f6bc41dd",
      "running_yes_shares": 266.1,
      "running_no_shares": 404.0,
      "running_yes_cost": 147.752,
      "running_no_cost": 157.24,
      "running_total_exposure": 304.992,
      "raw": {
        "proxyWallet": "0x6031b6eed1c97e853c6e0f03ad3ce3529351f96d",
        "asset": "91528401740238005717802973551490004353166851233063526555597421997428947532492",
        "conditionId": "0x920d65638f8b944418e35a41af586cbb01dbbd458dff1ce69a0291c6ef537e89",
        "outcomeIndex": 0
      }
    },
    {
      "trade_number": 49,
      "timestamp": 1765099247,
      "datetime": "2025-12-07 06:20:47",
      "action": "BUY",
      "outcome": "YES",
      "price": 0.54,
      "price_cents": 54.0,
      "shares": 16.0,
      "cost_usd": 8.64,
      "transaction_hash": "0x7782bf74678a1a5d843eb2c05e383105e12f9c618ad03c54b9cdf5912101438e",
      "running_yes_shares": 282.1,
      "running_no_shares": 404.0,
      "running_yes_cost": 156.392,
      "running_no_cost": 157.24,
      "running_total_exposure": 313.632,
      "raw": {
        "proxyWallet": "0x6031b6eed1c97e853c6e0f03ad3ce3529351f96d",
        "asset": "91528401740238005717802973551490004353166851233063526555597421997428947532492",
        "conditionId": "0x920d65638f8b944418e35a41af586cbb01dbbd458dff1ce69a0291c6ef537e89",
        "outcomeIndex": 0
      }
    },
    {
      "trade_number": 50,
      "timestamp": 1765099257,
      "datetime": "2025-12-07 06:20:57",
      "action": "BUY",
      "outcome": "YES",
      "price": 0.49,
      "price_cents": 49.0,
      "shares": 16.0,
      "cost_usd": 7.84,
      "transaction_hash": "0xa25f5eaa1108c858ea34293dacc7b4312781fe457f18794b8169d3acbfa36f40",
      "running_yes_shares": 298.1,
      "running_no_shares": 404.0,
      "running_yes_cost": 164.232,
      "running_no_cost": 157.24,
      "running_total_exposure": 321.472,
      "raw": {
        "proxyWallet": "0x6031b6eed1c97e853c6e0f03ad3ce3529351f96d",
        "asset": "91528401740238005717802973551490004353166851233063526555597421997428947532492",
        "conditionId": "0x920d65638f8b944418e35a41af586cbb01dbbd458dff1ce69a0291c6ef537e89",
        "outcomeIndex": 0
      }
    },
    {
      "trade_number": 51,
      "timestamp": 1765099267,
      "datetime": "2025-12-07 06:21:07",
      "action": "BUY",
      "outcome": "NO",
      "price": 0.58,
      "price_cents": 58.0,
      "shares": 16.0,
      "cost_usd": 9.28,
      "transaction_hash": "0xae3fafd0b4f46b02c5340d5450ad1846e0a5bd1bcd0746773e23fc45390dc89c",
      "running_yes_shares": 298.1,
      "running_no_shares": 420.0,
      "running_yes_cost": 164.232,
      "running_no_cost": 166.52,
      "running_total_exposure": 330.752,
      "raw": {
        "proxyWallet": "0x6031b6eed1c97e853c6e0f03ad3ce3529351f96d",
        "asset": "24171791432867916848656083222804673305751745875361756606303355044034777352842",
        "conditionId": "0x920d65638f8b944418e35a41af586cbb01dbbd458dff1ce69a0291c6ef537e89",
        "outcomeIndex": 1
      }
    },
    {
      "trade_number": 52,
      "timestamp": 1765099335,
      "datetime": "2025-12-07 06:22:15",
      "action": "BUY",
      "outcome": "YES",
      "price": 0.27,
      "price_cents": 27.0,
      "shares": 16.0,
      "cost_usd": 4.32,
      "transaction_hash": "0xc4f4ba3ca7fde13f763212f2ac11d35ccc6634d6f780465647e0bd299ae9ae0e",
      "running_yes_shares": 314.1,
      "running_no_shares": 420.0,
      "running_yes_cost": 168.552,
      "running_no_cost": 166.52,
      "running_total_exposure": 335.072,
      "raw": {
        "proxyWallet": "0x6031b6eed1c97e853c6e0f03ad3ce3529351f96d",
        "asset": "91528401740238005717802973551490004353166851233063526555597421997428947532492",
        "conditionId": "0x920d65638f8b944418e35a41af586cbb01dbbd458dff1ce69a0291c6ef537e89",
        "outcomeIndex": 0
      }
    },
    {
      "trade_number": 53,
      "timestamp": 1765099357,
      "datetime": "2025-12-07 06:22:37",
      "action": "BUY",
      "outcome": "YES",
      "price": 0.25,
      "price_cents": 25.0,
      "shares": 16.0,
      "cost_usd": 4.0,
      "transaction_hash": "0xc2729e5e76ce027838d75ea702d92eb4567352bde969ce0c1c5b215af1d7dfc7",
      "running_yes_shares": 330.1,
      "running_no_shares": 420.0,
      "running_yes_cost": 172.552,
      "running_no_cost": 166.52,
      "running_total_exposure": 339.072,
      "raw": {
        "proxyWallet": "0x6031b6eed1c97e853c6e0f03ad3ce3529351f96d",
        "asset": "91528401740238005717802973551490004353166851233063526555597421997428947532492",
        "conditionId": "0x920d65638f8b944418e35a41af586cbb01dbbd458dff1ce69a0291c6ef537e89",
        "outcomeIndex": 0
      }
    },
    {
      "trade_number": 54,
      "timestamp": 1765099357,
      "datetime": "2025-12-07 06:22:37",
      "action": "BUY",
      "outcome": "YES",
      "price": 0.25,
      "price_cents": 25.0,
      "shares": 16.0,
      "cost_usd": 4.0,
      "transaction_hash": "0xb02f218b9fee130c5f202d12a2a4fa66e33a925ad4fd47acd521722d6c00b180",
      "running_yes_shares": 346.1,
      "running_no_shares": 420.0,
      "running_yes_cost": 176.552,
      "running_no_cost": 166.52,
      "running_total_exposure": 343.072,
      "raw": {
        "proxyWallet": "0x6031b6eed1c97e853c6e0f03ad3ce3529351f96d",
        "asset": "91528401740238005717802973551490004353166851233063526555597421997428947532492",
        "conditionId": "0x920d65638f8b944418e35a41af586cbb01dbbd458dff1ce69a0291c6ef537e89",
        "outcomeIndex": 0
      }
    },
    {
      "trade_number": 55,
      "timestamp": 1765099357,
      "datetime": "2025-12-07 06:22:37",
      "action": "BUY",
      "outcome": "YES",
      "price": 0.25,
      "price_cents": 25.0,
      "shares": 16.0,
      "cost_usd": 4.0,
      "transaction_hash": "0x3ef483c1e9e1431295078d995463181855b34dda9577d0c43b018666b9f0a377",
      "running_yes_shares": 362.1,
      "running_no_shares": 420.0,
      "running_yes_cost": 180.552,
      "running_no_cost": 166.52,
      "running_total_exposure": 347.072,
      "raw": {
        "proxyWallet": "0x6031b6eed1c97e853c6e0f03ad3ce3529351f96d",
        "asset": "91528401740238005717802973551490004353166851233063526555597421997428947532492",
        "conditionId": "0x920d65638f8b944418e35a41af586cbb01dbbd458dff1ce69a0291c6ef537e89",
        "outcomeIndex": 0
      }
    },
    {
      "trade_number": 56,
      "timestamp": 1765099357,
      "datetime": "2025-12-07 06:22:37",
      "action": "BUY",
      "outcome": "YES",
      "price": 0.25,
      "price_cents": 25.0,
      "shares": 16.0,
      "cost_usd": 4.0,
      "transaction_hash": "0xf6e99055b8606b41f06ac0ee244ebee5d4fb596ab96e4af945e058282071bcbe",
      "running_yes_shares": 378.1,
      "running_no_shares": 420.0,
      "running_yes_cost": 184.552,
      "running_no_cost": 166.52,
      "running_total_exposure": 351.072,
      "raw": {
        "proxyWallet": "0x6031b6eed1c97e853c6e0f03ad3ce3529351f96d",
        "asset": "91528401740238005717802973551490004353166851233063526555597421997428947532492",
        "conditionId": "0x920d65638f8b944418e35a41af586cbb01dbbd458dff1ce69a0291c6ef537e89",
        "outcomeIndex": 0
      }
    },
    {
      "trade_number": 57,
      "timestamp": 1765099359,
      "datetime": "2025-12-07 06:22:39",
      "action": "BUY",
      "outcome": "YES",
      "price": 0.28,
      "price_cents": 28.0,
      "shares": 16.0,
      "cost_usd": 4.48,
      "transaction_hash": "0x445e17b657e63573a7cea63ee5a42d7ac8d2d9f6cc47a78b16962d71a9a97409",
      "running_yes_shares": 394.1,
      "running_no_shares": 420.0,
      "running_yes_cost": 189.032,
      "running_no_cost": 166.52,
      "running_total_exposure": 355.552,
      "raw": {
        "proxyWallet": "0x6031b6eed1c97e853c6e0f03ad3ce3529351f96d",
        "asset": "91528401740238005717802973551490004353166851233063526555597421997428947532492",
        "conditionId": "0x920d65638f8b944418e35a41af586cbb01dbbd458dff1ce69a0291c6ef537e89",
        "outcomeIndex": 0
      }
    },
    {
      "trade_number": 58,
      "timestamp": 1765099393,
      "datetime": "2025-12-07 06:23:13",
      "action": "BUY",
      "outcome": "YES",
      "price": 0.34,
      "price_cents": 34.0,
      "shares": 16.0,
      "cost_usd": 5.44,
      "transaction_hash": "0xbb104aab14f132c7c1915fb77c578120e85e1e070cdce87bbe04c1bb35741b75",
      "running_yes_shares": 410.1,
      "running_no_shares": 420.0,
      "running_yes_cost": 194.472,
      "running_no_cost": 166.52,
      "running_total_exposure": 360.992,
      "raw": {
        "proxyWallet": "0x6031b6eed1c97e853c6e0f03ad3ce3529351f96d",
        "asset": "91528401740238005717802973551490004353166851233063526555597421997428947532492",
        "conditionId": "0x920d65638f8b944418e35a41af586cbb01dbbd458dff1ce69a0291c6ef537e89",
        "outcomeIndex": 0
      }
    },
    {
      "trade_number": 59,
      "timestamp": 1765099427,
      "datetime": "2025-12-07 06:23:47",
      "action": "BUY",
      "outcome": "YES",
      "price": 0.28,
      "price_cents": 28.0,
      "shares": 16.0,
      "cost_usd": 4.48,
      "transaction_hash": "0x58768534b292c3b92aebecea2345e93649b737eb0414896dcb3b83c5b0d8b6ba",
      "running_yes_shares": 426.1,
      "running_no_shares": 420.0,
      "running_yes_cost": 198.952,
      "running_no_cost": 166.52,
      "running_total_exposure": 365.472,
      "raw": {
        "proxyWallet": "0x6031b6eed1c97e853c6e0f03ad3ce3529351f96d",
        "asset": "91528401740238005717802973551490004353166851233063526555597421997428947532492",
        "conditionId": "0x920d65638f8b944418e35a41af586cbb01dbbd458dff1ce69a0291c6ef537e89",
        "outcomeIndex": 0
      }
    },
    {
      "trade_number": 60,
      "timestamp": 1765099427,
      "datetime": "2025-12-07 06:23:47",
      "action": "BUY",
      "outcome": "YES",
      "price": 0.28,
      "price_cents": 28.0,
      "shares": 16.0,
      "cost_usd": 4.48,
      "transaction_hash": "0x4d0f5bf745d125c984c1756cadc0601c99bcd401a48718f269d2a3ec23efc480",
      "running_yes_shares": 442.1,
      "running_no_shares": 420.0,
      "running_yes_cost": 203.432,
      "running_no_cost": 166.52,
      "running_total_exposure": 369.952,
      "raw": {
        "proxyWallet": "0x6031b6eed1c97e853c6e0f03ad3ce3529351f96d",
        "asset": "91528401740238005717802973551490004353166851233063526555597421997428947532492",
        "conditionId": "0x920d65638f8b944418e35a41af586cbb01dbbd458dff1ce69a0291c6ef537e89",
        "outcomeIndex": 0
      }
    },
    {
      "trade_number": 61,
      "timestamp": 1765099439,
      "datetime": "2025-12-07 06:23:59",
      "action": "BUY",
      "outcome": "NO",
      "price": 0.73,
      "price_cents": 73.0,
      "shares": 10.0,
      "cost_usd": 7.3,
      "transaction_hash": "0xbc2e585a5744b2eade50712191451fc76e94fbd855f5ad58f8a703427971dd0e",
      "running_yes_shares": 442.1,
      "running_no_shares": 430.0,
      "running_yes_cost": 203.432,
      "running_no_cost": 173.82,
      "running_total_exposure": 377.252,
      "raw": {
        "proxyWallet": "0x6031b6eed1c97e853c6e0f03ad3ce3529351f96d",
        "asset": "24171791432867916848656083222804673305751745875361756606303355044034777352842",
        "conditionId": "0x920d65638f8b944418e35a41af586cbb01dbbd458dff1ce69a0291c6ef537e89",
        "outcomeIndex": 1
      }
    },
    {
      "trade_number": 62,
      "timestamp": 1765099479,
      "datetime": "2025-12-07 06:24:39",
      "action": "BUY",
      "outcome": "YES",
      "price": 0.18,
      "price_cents": 18.0,
      "shares": 16.0,
      "cost_usd": 2.88,
      "transaction_hash": "0xc8f0eb7b3bb1e6931d6155dd7caf70fcfbd564f966c32012b495d2d9221951a6",
      "running_yes_shares": 458.1,
      "running_no_shares": 430.0,
      "running_yes_cost": 206.312,
      "running_no_cost": 173.82,
      "running_total_exposure": 380.132,
      "raw": {
        "proxyWallet": "0x6031b6eed1c97e853c6e0f03ad3ce3529351f96d",
        "asset": "91528401740238005717802973551490004353166851233063526555597421997428947532492",
        "conditionId": "0x920d65638f8b944418e35a41af586cbb01dbbd458dff1ce69a0291c6ef537e89",
        "outcomeIndex": 0
      }
    },
    {
      "trade_number": 63,
      "timestamp": 1765099479,
      "datetime": "2025-12-07 06:24:39",
      "action": "BUY",
      "outcome": "YES",
      "price": 0.18,
      "price_cents": 18.0,
      "shares": 16.0,
      "cost_usd": 2.88,
      "transaction_hash": "0x7310d51afe660d071f205901d3a3599e30c2a6670b35d01b7e3383bc4f39a00c",
      "running_yes_shares": 474.1,
      "running_no_shares": 430.0,
      "running_yes_cost": 209.192,
      "running_no_cost": 173.82,
      "running_total_exposure": 383.012,
      "raw": {
        "proxyWallet": "0x6031b6eed1c97e853c6e0f03ad3ce3529351f96d",
        "asset": "91528401740238005717802973551490004353166851233063526555597421997428947532492",
        "conditionId": "0x920d65638f8b944418e35a41af586cbb01dbbd458dff1ce69a0291c6ef537e89",
        "outcomeIndex": 0
      }
    },
    {
      "trade_number": 64,
      "timestamp": 1765099479,
      "datetime": "2025-12-07 06:24:39",
      "action": "BUY",
      "outcome": "YES",
      "price": 0.18,
      "price_cents": 18.0,
      "shares": 16.0,
      "cost_usd": 2.88,
      "transaction_hash": "0xe2390f7e6dc50186a19553ff38e76a3a0c75836c5b0cc8eed68a30667b650adc",
      "running_yes_shares": 490.1,
      "running_no_shares": 430.0,
      "running_yes_cost": 212.072,
      "running_no_cost": 173.82,
      "running_total_exposure": 385.892,
      "raw": {
        "proxyWallet": "0x6031b6eed1c97e853c6e0f03ad3ce3529351f96d",
        "asset": "91528401740238005717802973551490004353166851233063526555597421997428947532492",
        "conditionId": "0x920d65638f8b944418e35a41af586cbb01dbbd458dff1ce69a0291c6ef537e89",
        "outcomeIndex": 0
      }
    },
    {
      "trade_number": 65,
      "timestamp": 1765099479,
      "datetime": "2025-12-07 06:24:39",
      "action": "BUY",
      "outcome": "YES",
      "price": 0.18,
      "price_cents": 18.0,
      "shares": 16.0,
      "cost_usd": 2.88,
      "transaction_hash": "0x5e19d705a8216cadcee81113ba9fd73f8f24ce63f8819ffb1fe829dd0323b7a6",
      "running_yes_shares": 506.1,
      "running_no_shares": 430.0,
      "running_yes_cost": 214.952,
      "running_no_cost": 173.82,
      "running_total_exposure": 388.772,
      "raw": {
        "proxyWallet": "0x6031b6eed1c97e853c6e0f03ad3ce3529351f96d",
        "asset": "91528401740238005717802973551490004353166851233063526555597421997428947532492",
        "conditionId": "0x920d65638f8b944418e35a41af586cbb01dbbd458dff1ce69a0291c6ef537e89",
        "outcomeIndex": 0
      }
    },
    {
      "trade_number": 66,
      "timestamp": 1765099481,
      "datetime": "2025-12-07 06:24:41",
      "action": "BUY",
      "outcome": "YES",
      "price": 0.14,
      "price_cents": 14.0,
      "shares": 16.0,
      "cost_usd": 2.24,
      "transaction_hash": "0x91f7702b74901daeedcd24c0401164f13f2b03b41c5c2abed922007d416c64ca",
      "running_yes_shares": 522.1,
      "running_no_shares": 430.0,
      "running_yes_cost": 217.192,
      "running_no_cost": 173.82,
      "running_total_exposure": 391.012,
      "raw": {
        "proxyWallet": "0x6031b6eed1c97e853c6e0f03ad3ce3529351f96d",
        "asset": "91528401740238005717802973551490004353166851233063526555597421997428947532492",
        "conditionId": "0x920d65638f8b944418e35a41af586cbb01dbbd458dff1ce69a0291c6ef537e89",
        "outcomeIndex": 0
      }
    },
    {
      "trade_number": 67,
      "timestamp": 1765099481,
      "datetime": "2025-12-07 06:24:41",
      "action": "BUY",
      "outcome": "YES",
      "price": 0.14,
      "price_cents": 14.0,
      "shares": 16.0,
      "cost_usd": 2.24,
      "transaction_hash": "0x61b9218c3d5142f388d19e41b695cf8b42d86a12e66935dad2390e497abd2487",
      "running_yes_shares": 538.1,
      "running_no_shares": 430.0,
      "running_yes_cost": 219.432,
      "running_no_cost": 173.82,
      "running_total_exposure": 393.252,
      "raw": {
        "proxyWallet": "0x6031b6eed1c97e853c6e0f03ad3ce3529351f96d",
        "asset": "91528401740238005717802973551490004353166851233063526555597421997428947532492",
        "conditionId": "0x920d65638f8b944418e35a41af586cbb01dbbd458dff1ce69a0291c6ef537e89",
        "outcomeIndex": 0
      }
    },
    {
      "trade_number": 68,
      "timestamp": 1765099509,
      "datetime": "2025-12-07 06:25:09",
      "action": "BUY",
      "outcome": "NO",
      "price": 0.84,
      "price_cents": 84.0,
      "shares": 16.0,
      "cost_usd": 13.44,
      "transaction_hash": "0xf643022fb66641825c44e8b7f7dcd5b8fe09a2f9f996fd91099baafc255000ed",
      "running_yes_shares": 538.1,
      "running_no_shares": 446.0,
      "running_yes_cost": 219.432,
      "running_no_cost": 187.26,
      "running_total_exposure": 406.692,
      "raw": {
        "proxyWallet": "0x6031b6eed1c97e853c6e0f03ad3ce3529351f96d",
        "asset": "24171791432867916848656083222804673305751745875361756606303355044034777352842",
        "conditionId": "0x920d65638f8b944418e35a41af586cbb01dbbd458dff1ce69a0291c6ef537e89",
        "outcomeIndex": 1
      }
    },
    {
      "trade_number": 69,
      "timestamp": 1765099515,
      "datetime": "2025-12-07 06:25:15",
      "action": "BUY",
      "outcome": "YES",
      "price": 0.14,
      "price_cents": 14.0,
      "shares": 16.0,
      "cost_usd": 2.24,
      "transaction_hash": "0xcea98bdafb2f0f8f5bb3467445dcb0ea064ef738583b3d642d7eeaf6cd0e7426",
      "running_yes_shares": 554.1,
      "running_no_shares": 446.0,
      "running_yes_cost": 221.672,
      "running_no_cost": 187.26,
      "running_total_exposure": 408.932,
      "raw": {
        "proxyWallet": "0x6031b6eed1c97e853c6e0f03ad3ce3529351f96d",
        "asset": "91528401740238005717802973551490004353166851233063526555597421997428947532492",
        "conditionId": "0x920d65638f8b944418e35a41af586cbb01dbbd458dff1ce69a0291c6ef537e89",
        "outcomeIndex": 0
      }
    },
    {
      "trade_number": 70,
      "timestamp": 1765099541,
      "datetime": "2025-12-07 06:25:41",
      "action": "BUY",
      "outcome": "YES",
      "price": 0.16,
      "price_cents": 16.0,
      "shares": 5.0,
      "cost_usd": 0.8,
      "transaction_hash": "0x1102642a9a2d5395e38829980dd321491219fdde83e1930050e36887f4cd1f2a",
      "running_yes_shares": 559.1,
      "running_no_shares": 446.0,
      "running_yes_cost": 222.472,
      "running_no_cost": 187.26,
      "running_total_exposure": 409.732,
      "raw": {
        "proxyWallet": "0x6031b6eed1c97e853c6e0f03ad3ce3529351f96d",
        "asset": "91528401740238005717802973551490004353166851233063526555597421997428947532492",
        "conditionId": "0x920d65638f8b944418e35a41af586cbb01dbbd458dff1ce69a0291c6ef537e89",
        "outcomeIndex": 0
      }
    },
    {
      "trade_number": 71,
      "timestamp": 1765099569,
      "datetime": "2025-12-07 06:26:09",
      "action": "BUY",
      "outcome": "YES",
      "price": 0.2,
      "price_cents": 20.0,
      "shares": 10.0,
      "cost_usd": 2.0,
      "transaction_hash": "0xbb2c90791ff71ebc349b794e3e456049089cc39b48eefc3e249724dab2623d34",
      "running_yes_shares": 569.1,
      "running_no_shares": 446.0,
      "running_yes_cost": 224.472,
      "running_no_cost": 187.26,
      "running_total_exposure": 411.732,
      "raw": {
        "proxyWallet": "0x6031b6eed1c97e853c6e0f03ad3ce3529351f96d",
        "asset": "91528401740238005717802973551490004353166851233063526555597421997428947532492",
        "conditionId": "0x920d65638f8b944418e35a41af586cbb01dbbd458dff1ce69a0291c6ef537e89",
        "outcomeIndex": 0
      }
    },
    {
      "trade_number": 72,
      "timestamp": 1765099569,
      "datetime": "2025-12-07 06:26:09",
      "action": "BUY",
      "outcome": "YES",
      "price": 0.19,
      "price_cents": 19.0,
      "shares": 15.0,
      "cost_usd": 2.85,
      "transaction_hash": "0xf2978c7d246b06c5c2676626af9c82c2d4dcd2b2fca26cdd62e3e12b3041c554",
      "running_yes_shares": 584.1,
      "running_no_shares": 446.0,
      "running_yes_cost": 227.322,
      "running_no_cost": 187.26,
      "running_total_exposure": 414.582,
      "raw": {
        "proxyWallet": "0x6031b6eed1c97e853c6e0f03ad3ce3529351f96d",
        "asset": "91528401740238005717802973551490004353166851233063526555597421997428947532492",
        "conditionId": "0x920d65638f8b944418e35a41af586cbb01dbbd458dff1ce69a0291c6ef537e89",
        "outcomeIndex": 0
      }
    },
    {
      "trade_number": 73,
      "timestamp": 1765099589,
      "datetime": "2025-12-07 06:26:29",
      "action": "BUY",
      "outcome": "YES",
      "price": 0.24,
      "price_cents": 24.0,
      "shares": 15.0,
      "cost_usd": 3.6,
      "transaction_hash": "0xb4322e69207dc5ffd2ffa04d505d29f38b4941b6d0681f22c8f742b46db41036",
      "running_yes_shares": 599.1,
      "running_no_shares": 446.0,
      "running_yes_cost": 230.922,
      "running_no_cost": 187.26,
      "running_total_exposure": 418.182,
      "raw": {
        "proxyWallet": "0x6031b6eed1c97e853c6e0f03ad3ce3529351f96d",
        "asset": "91528401740238005717802973551490004353166851233063526555597421997428947532492",
        "conditionId": "0x920d65638f8b944418e35a41af586cbb01dbbd458dff1ce69a0291c6ef537e89",
        "outcomeIndex": 0
      }
    },
    {
      "trade_number": 74,
      "timestamp": 1765099589,
      "datetime": "2025-12-07 06:26:29",
      "action": "BUY",
      "outcome": "YES",
      "price": 0.23,
      "price_cents": 23.0,
      "shares": 15.0,
      "cost_usd": 3.45,
      "transaction_hash": "0x30ce0f4a05fb19404e87ed48bf2386027edd6941a3107f7927aee61b66bbb1a0",
      "running_yes_shares": 614.1,
      "running_no_shares": 446.0,
      "running_yes_cost": 234.372,
      "running_no_cost": 187.26,
      "running_total_exposure": 421.632,
      "raw": {
        "proxyWallet": "0x6031b6eed1c97e853c6e0f03ad3ce3529351f96d",
        "asset": "91528401740238005717802973551490004353166851233063526555597421997428947532492",
        "conditionId": "0x920d65638f8b944418e35a41af586cbb01dbbd458dff1ce69a0291c6ef537e89",
        "outcomeIndex": 0
      }
    },
    {
      "trade_number": 75,
      "timestamp": 1765099621,
      "datetime": "2025-12-07 06:27:01",
      "action": "BUY",
      "outcome": "YES",
      "price": 0.26,
      "price_cents": 26.0,
      "shares": 4.0,
      "cost_usd": 1.04,
      "transaction_hash": "0xc1143e40943634eb4d273c8bf2c5463cb6f95d9530df1a711350db047c83c632",
      "running_yes_shares": 618.1,
      "running_no_shares": 446.0,
      "running_yes_cost": 235.412,
      "running_no_cost": 187.26,
      "running_total_exposure": 422.672,
      "raw": {
        "proxyWallet": "0x6031b6eed1c97e853c6e0f03ad3ce3529351f96d",
        "asset": "91528401740238005717802973551490004353166851233063526555597421997428947532492",
        "conditionId": "0x920d65638f8b944418e35a41af586cbb01dbbd458dff1ce69a0291c6ef537e89",
        "outcomeIndex": 0
      }
    },
    {
      "trade_number": 76,
      "timestamp": 1765099621,
      "datetime": "2025-12-07 06:27:01",
      "action": "BUY",
      "outcome": "YES",
      "price": 0.26,
      "price_cents": 26.0,
      "shares": 16.0,
      "cost_usd": 4.16,
      "transaction_hash": "0xe30eb7ffd0e8b664702d705f3f35a03210a5428df7af1c640cb70e15c75586ad",
      "running_yes_shares": 634.1,
      "running_no_shares": 446.0,
      "running_yes_cost": 239.572,
      "running_no_cost": 187.26,
      "running_total_exposure": 426.832,
      "raw": {
        "proxyWallet": "0x6031b6eed1c97e853c6e0f03ad3ce3529351f96d",
        "asset": "91528401740238005717802973551490004353166851233063526555597421997428947532492",
        "conditionId": "0x920d65638f8b944418e35a41af586cbb01dbbd458dff1ce69a0291c6ef537e89",
        "outcomeIndex": 0
      }
    },
    {
      "trade_number": 77,
      "timestamp": 1765099671,
      "datetime": "2025-12-07 06:27:51",
      "action": "BUY",
      "outcome": "NO",
      "price": 0.78,
      "price_cents": 78.0,
      "shares": 4.02,
      "cost_usd": 3.1356,
      "transaction_hash": "0x9f22e5774f993ba6922e920c7e2bd9e71143014a77311cdd246a19eaca996783",
      "running_yes_shares": 634.1,
      "running_no_shares": 450.02,
      "running_yes_cost": 239.572,
      "running_no_cost": 190.3956,
      "running_total_exposure": 429.9676,
      "raw": {
        "proxyWallet": "0x6031b6eed1c97e853c6e0f03ad3ce3529351f96d",
        "asset": "24171791432867916848656083222804673305751745875361756606303355044034777352842",
        "conditionId": "0x920d65638f8b944418e35a41af586cbb01dbbd458dff1ce69a0291c6ef537e89",
        "outcomeIndex": 1
      }
    },
    {
      "trade_number": 78,
      "timestamp": 1765099681,
      "datetime": "2025-12-07 06:28:01",
      "action": "BUY",
      "outcome": "NO",
      "price": 0.8,
      "price_cents": 80.0,
      "shares": 5.0,
      "cost_usd": 4.0,
      "transaction_hash": "0xb2fc90340573fe9d101eac9d345729485bcfc774092644d87dad6c01cfdf9f21",
      "running_yes_shares": 634.1,
      "running_no_shares": 455.02,
      "running_yes_cost": 239.572,
      "running_no_cost": 194.3956,
      "running_total_exposure": 433.9676,
      "raw": {
        "proxyWallet": "0x6031b6eed1c97e853c6e0f03ad3ce3529351f96d",
        "asset": "24171791432867916848656083222804673305751745875361756606303355044034777352842",
        "conditionId": "0x920d65638f8b944418e35a41af586cbb01dbbd458dff1ce69a0291c6ef537e89",
        "outcomeIndex": 1
      }
    },
    {
      "trade_number": 79,
      "timestamp": 1765099897,
      "datetime": "2025-12-07 06:31:37",
      "action": "BUY",
      "outcome": "YES",
      "price": 0.24,
      "price_cents": 24.0,
      "shares": 15.0,
      "cost_usd": 3.6,
      "transaction_hash": "0x3054e8905b659a1ad3ababf25ea8bd130ce20fe49a6021e91008e6762f14e1f2",
      "running_yes_shares": 649.1,
      "running_no_shares": 455.02,
      "running_yes_cost": 243.172,
      "running_no_cost": 194.3956,
      "running_total_exposure": 437.5676,
      "raw": {
        "proxyWallet": "0x6031b6eed1c97e853c6e0f03ad3ce3529351f96d",
        "asset": "91528401740238005717802973551490004353166851233063526555597421997428947532492",
        "conditionId": "0x920d65638f8b944418e35a41af586cbb01dbbd458dff1ce69a0291c6ef537e89",
        "outcomeIndex": 0
      }
    },
    {
      "trade_number": 80,
      "timestamp": 1765099985,
      "datetime": "2025-12-07 06:33:05",
      "action": "BUY",
      "outcome": "NO",
      "price": 0.7,
      "price_cents": 70.0,
      "shares": 15.0,
      "cost_usd": 10.5,
      "transaction_hash": "0xac72cfca8186bd793bb0c5fab5201b54c910851a3ede4aa537fdd51f068dae4b",
      "running_yes_shares": 649.1,
      "running_no_shares": 470.02,
      "running_yes_cost": 243.172,
      "running_no_cost": 204.8956,
      "running_total_exposure": 448.0676,
      "raw": {
        "proxyWallet": "0x6031b6eed1c97e853c6e0f03ad3ce3529351f96d",
        "asset": "24171791432867916848656083222804673305751745875361756606303355044034777352842",
        "conditionId": "0x920d65638f8b944418e35a41af586cbb01dbbd458dff1ce69a0291c6ef537e89",
        "outcomeIndex": 1
      }
    },
    {
      "trade_number": 81,
      "timestamp": 1765100085,
      "datetime": "2025-12-07 06:34:45",
      "action": "BUY",
      "outcome": "NO",
      "price": 0.6,
      "price_cents": 60.0,
      "shares": 15.0,
      "cost_usd": 9.0,
      "transaction_hash": "0xa4d2359c2028fcdaaeda6f7fd854040b896c072714f06bd905f668a40d9dacf0",
      "running_yes_shares": 649.1,
      "running_no_shares": 485.02,
      "running_yes_cost": 243.172,
      "running_no_cost": 213.8956,
      "running_total_exposure": 457.0676,
      "raw": {
        "proxyWallet": "0x6031b6eed1c97e853c6e0f03ad3ce3529351f96d",
        "asset": "24171791432867916848656083222804673305751745875361756606303355044034777352842",
        "conditionId": "0x920d65638f8b944418e35a41af586cbb01dbbd458dff1ce69a0291c6ef537e89",
        "outcomeIndex": 1
      }
    },
    {
      "trade_number": 82,
      "timestamp": 1765100085,
      "datetime": "2025-12-07 06:34:45",
      "action": "BUY",
      "outcome": "NO",
      "price": 0.6,
      "price_cents": 60.0,
      "shares": 15.0,
      "cost_usd": 9.0,
      "transaction_hash": "0xcd1da00673e51f81c09d1d9f147b51690518ae71e1a792ef8d7c5a7aab4747e2",
      "running_yes_shares": 649.1,
      "running_no_shares": 500.02,
      "running_yes_cost": 243.172,
      "running_no_cost": 222.8956,
      "running_total_exposure": 466.0676,
      "raw": {
        "proxyWallet": "0x6031b6eed1c97e853c6e0f03ad3ce3529351f96d",
        "asset": "24171791432867916848656083222804673305751745875361756606303355044034777352842",
        "conditionId": "0x920d65638f8b944418e35a41af586cbb01dbbd458dff1ce69a0291c6ef537e89",
        "outcomeIndex": 1
      }
    },
    {
      "trade_number": 83,
      "timestamp": 1765100089,
      "datetime": "2025-12-07 06:34:49",
      "action": "BUY",
      "outcome": "NO",
      "price": 0.6,
      "price_cents": 60.0,
      "shares": 15.0,
      "cost_usd": 9.0,
      "transaction_hash": "0xd9aeea8f2e15ce27f7b128dd79b674eeef160552485ec40450e0fcab1d60a2c9",
      "running_yes_shares": 649.1,
      "running_no_shares": 515.02,
      "running_yes_cost": 243.172,
      "running_no_cost": 231.8956,
      "running_total_exposure": 475.0676,
      "raw": {
        "proxyWallet": "0x6031b6eed1c97e853c6e0f03ad3ce3529351f96d",
        "asset": "24171791432867916848656083222804673305751745875361756606303355044034777352842",
        "conditionId": "0x920d65638f8b944418e35a41af586cbb01dbbd458dff1ce69a0291c6ef537e89",
        "outcomeIndex": 1
      }
    },
    {
      "trade_number": 84,
      "timestamp": 1765100115,
      "datetime": "2025-12-07 06:35:15",
      "action": "BUY",
      "outcome": "YES",
      "price": 0.4,
      "price_cents": 40.0,
      "shares": 15.0,
      "cost_usd": 6.0,
      "transaction_hash": "0xb86bee8e2a1e420f4a79de7ef7ca15f058812b0588dcfde3c04ee70ebc662fe8",
      "running_yes_shares": 664.1,
      "running_no_shares": 515.02,
      "running_yes_cost": 249.172,
      "running_no_cost": 231.8956,
      "running_total_exposure": 481.0676,
      "raw": {
        "proxyWallet": "0x6031b6eed1c97e853c6e0f03ad3ce3529351f96d",
        "asset": "91528401740238005717802973551490004353166851233063526555597421997428947532492",
        "conditionId": "0x920d65638f8b944418e35a41af586cbb01dbbd458dff1ce69a0291c6ef537e89",
        "outcomeIndex": 0
      }
    },
    {
      "trade_number": 85,
      "timestamp": 1765100131,
      "datetime": "2025-12-07 06:35:31",
      "action": "BUY",
      "outcome": "YES",
      "price": 0.32,
      "price_cents": 32.0,
      "shares": 15.0,
      "cost_usd": 4.8,
      "transaction_hash": "0x1f71cee8ee720e5e30fef9b87d6db471c6c69a6d572f7d3b9bbccc2bdb64a3c5",
      "running_yes_shares": 679.1,
      "running_no_shares": 515.02,
      "running_yes_cost": 253.972,
      "running_no_cost": 231.8956,
      "running_total_exposure": 485.8676,
      "raw": {
        "proxyWallet": "0x6031b6eed1c97e853c6e0f03ad3ce3529351f96d",
        "asset": "91528401740238005717802973551490004353166851233063526555597421997428947532492",
        "conditionId": "0x920d65638f8b944418e35a41af586cbb01dbbd458dff1ce69a0291c6ef537e89",
        "outcomeIndex": 0
      }
    },
    {
      "trade_number": 86,
      "timestamp": 1765100131,
      "datetime": "2025-12-07 06:35:31",
      "action": "BUY",
      "outcome": "YES",
      "price": 0.32,
      "price_cents": 32.0,
      "shares": 15.0,
      "cost_usd": 4.8,
      "transaction_hash": "0x6438cf55ef834a2c94c64dc07d7c253a54035f65c6a11d96abc5fc06bc017bbd",
      "running_yes_shares": 694.1,
      "running_no_shares": 515.02,
      "running_yes_cost": 258.772,
      "running_no_cost": 231.8956,
      "running_total_exposure": 490.6676,
      "raw": {
        "proxyWallet": "0x6031b6eed1c97e853c6e0f03ad3ce3529351f96d",
        "asset": "91528401740238005717802973551490004353166851233063526555597421997428947532492",
        "conditionId": "0x920d65638f8b944418e35a41af586cbb01dbbd458dff1ce69a0291c6ef537e89",
        "outcomeIndex": 0
      }
    },
    {
      "trade_number": 87,
      "timestamp": 1765100131,
      "datetime": "2025-12-07 06:35:31",
      "action": "BUY",
      "outcome": "YES",
      "price": 0.32,
      "price_cents": 32.0,
      "shares": 15.0,
      "cost_usd": 4.8,
      "transaction_hash": "0xb4797906b32ab42b845fe5fe8df404ff0a01ed54f0a3bdd417fa7d9310c34d5e",
      "running_yes_shares": 709.1,
      "running_no_shares": 515.02,
      "running_yes_cost": 263.572,
      "running_no_cost": 231.8956,
      "running_total_exposure": 495.4676,
      "raw": {
        "proxyWallet": "0x6031b6eed1c97e853c6e0f03ad3ce3529351f96d",
        "asset": "91528401740238005717802973551490004353166851233063526555597421997428947532492",
        "conditionId": "0x920d65638f8b944418e35a41af586cbb01dbbd458dff1ce69a0291c6ef537e89",
        "outcomeIndex": 0
      }
    },
    {
      "trade_number": 88,
      "timestamp": 1765100131,
      "datetime": "2025-12-07 06:35:31",
      "action": "BUY",
      "outcome": "YES",
      "price": 0.32,
      "price_cents": 32.0,
      "shares": 15.0,
      "cost_usd": 4.8,
      "transaction_hash": "0x43d4d44b3b64eb7bb1d1a99edaa5d114fe635f93eb357e0a6efcb40172ba3371",
      "running_yes_shares": 724.1,
      "running_no_shares": 515.02,
      "running_yes_cost": 268.372,
      "running_no_cost": 231.8956,
      "running_total_exposure": 500.2676,
      "raw": {
        "proxyWallet": "0x6031b6eed1c97e853c6e0f03ad3ce3529351f96d",
        "asset": "91528401740238005717802973551490004353166851233063526555597421997428947532492",
        "conditionId": "0x920d65638f8b944418e35a41af586cbb01dbbd458dff1ce69a0291c6ef537e89",
        "outcomeIndex": 0
      }
    },
    {
      "trade_number": 89,
      "timestamp": 1765100191,
      "datetime": "2025-12-07 06:36:31",
      "action": "BUY",
      "outcome": "NO",
      "price": 0.74,
      "price_cents": 74.0,
      "shares": 8.0,
      "cost_usd": 5.92,
      "transaction_hash": "0x7d8720d517b4fa9d7042c6027b67ba8218afb632759aa68f10712c1a99fd2f12",
      "running_yes_shares": 724.1,
      "running_no_shares": 523.02,
      "running_yes_cost": 268.372,
      "running_no_cost": 237.8156,
      "running_total_exposure": 506.1876,
      "raw": {
        "proxyWallet": "0x6031b6eed1c97e853c6e0f03ad3ce3529351f96d",
        "asset": "24171791432867916848656083222804673305751745875361756606303355044034777352842",
        "conditionId": "0x920d65638f8b944418e35a41af586cbb01dbbd458dff1ce69a0291c6ef537e89",
        "outcomeIndex": 1
      }
    },
    {
      "trade_number": 90,
      "timestamp": 1765100245,
      "datetime": "2025-12-07 06:37:25",
      "action": "BUY",
      "outcome": "NO",
      "price": 0.68,
      "price_cents": 68.0,
      "shares": 15.0,
      "cost_usd": 10.2,
      "transaction_hash": "0x7854bd6cebac59608c626a580c2ec0c49471fe7d7d9accb9dabccdefab4ce9cb",
      "running_yes_shares": 724.1,
      "running_no_shares": 538.02,
      "running_yes_cost": 268.372,
      "running_no_cost": 248.0156,
      "running_total_exposure": 516.3876,
      "raw": {
        "proxyWallet": "0x6031b6eed1c97e853c6e0f03ad3ce3529351f96d",
        "asset": "24171791432867916848656083222804673305751745875361756606303355044034777352842",
        "conditionId": "0x920d65638f8b944418e35a41af586cbb01dbbd458dff1ce69a0291c6ef537e89",
        "outcomeIndex": 1
      }
    },
    {
      "trade_number": 91,
      "timestamp": 1765100245,
      "datetime": "2025-12-07 06:37:25",
      "action": "BUY",
      "outcome": "NO",
      "price": 0.68,
      "price_cents": 68.0,
      "shares": 15.0,
      "cost_usd": 10.2,
      "transaction_hash": "0xb194ee74b15e2022fafd4414c00e9526db93c22fa6816ead2c335db4066d36c7",
      "running_yes_shares": 724.1,
      "running_no_shares": 553.02,
      "running_yes_cost": 268.372,
      "running_no_cost": 258.2156,
      "running_total_exposure": 526.5876,
      "raw": {
        "proxyWallet": "0x6031b6eed1c97e853c6e0f03ad3ce3529351f96d",
        "asset": "24171791432867916848656083222804673305751745875361756606303355044034777352842",
        "conditionId": "0x920d65638f8b944418e35a41af586cbb01dbbd458dff1ce69a0291c6ef537e89",
        "outcomeIndex": 1
      }
    },
    {
      "trade_number": 92,
      "timestamp": 1765100245,
      "datetime": "2025-12-07 06:37:25",
      "action": "BUY",
      "outcome": "NO",
      "price": 0.68,
      "price_cents": 68.0,
      "shares": 6.45,
      "cost_usd": 4.386,
      "transaction_hash": "0x10ab968446f52b5250af176cfc39a7463b363569c1cab42d1cc63981f8f4b168",
      "running_yes_shares": 724.1,
      "running_no_shares": 559.47,
      "running_yes_cost": 268.372,
      "running_no_cost": 262.6016,
      "running_total_exposure": 530.9736,
      "raw": {
        "proxyWallet": "0x6031b6eed1c97e853c6e0f03ad3ce3529351f96d",
        "asset": "24171791432867916848656083222804673305751745875361756606303355044034777352842",
        "conditionId": "0x920d65638f8b944418e35a41af586cbb01dbbd458dff1ce69a0291c6ef537e89",
        "outcomeIndex": 1
      }
    },
    {
      "trade_number": 93,
      "timestamp": 1765100245,
      "datetime": "2025-12-07 06:37:25",
      "action": "BUY",
      "outcome": "NO",
      "price": 0.68,
      "price_cents": 68.0,
      "shares": 15.0,
      "cost_usd": 10.2,
      "transaction_hash": "0x23b55ca20616527e8b76bf38e0551f5f37b31c2d5f7655daa9ba6da9dd74e931",
      "running_yes_shares": 724.1,
      "running_no_shares": 574.47,
      "running_yes_cost": 268.372,
      "running_no_cost": 272.8016,
      "running_total_exposure": 541.1736,
      "raw": {
        "proxyWallet": "0x6031b6eed1c97e853c6e0f03ad3ce3529351f96d",
        "asset": "24171791432867916848656083222804673305751745875361756606303355044034777352842",
        "conditionId": "0x920d65638f8b944418e35a41af586cbb01dbbd458dff1ce69a0291c6ef537e89",
        "outcomeIndex": 1
      }
    },
    {
      "trade_number": 94,
      "timestamp": 1765100245,
      "datetime": "2025-12-07 06:37:25",
      "action": "BUY",
      "outcome": "NO",
      "price": 0.68,
      "price_cents": 68.0,
      "shares": 15.0,
      "cost_usd": 10.2,
      "transaction_hash": "0xa44f2e4fe6e2156d4c4c7c70955b0d712b0400a5f3d1f7ef83fb9c844aac3855",
      "running_yes_shares": 724.1,
      "running_no_shares": 589.47,
      "running_yes_cost": 268.372,
      "running_no_cost": 283.0016,
      "running_total_exposure": 551.3736,
      "raw": {
        "proxyWallet": "0x6031b6eed1c97e853c6e0f03ad3ce3529351f96d",
        "asset": "24171791432867916848656083222804673305751745875361756606303355044034777352842",
        "conditionId": "0x920d65638f8b944418e35a41af586cbb01dbbd458dff1ce69a0291c6ef537e89",
        "outcomeIndex": 1
      }
    },
    {
      "trade_number": 95,
      "timestamp": 1765100245,
      "datetime": "2025-12-07 06:37:25",
      "action": "BUY",
      "outcome": "NO",
      "price": 0.68,
      "price_cents": 68.0,
      "shares": 15.0,
      "cost_usd": 10.2,
      "transaction_hash": "0x13f7d630626057516d2d6c8be2526376f1cff1d00613d0b9b3f434f9b0c591bb",
      "running_yes_shares": 724.1,
      "running_no_shares": 604.47,
      "running_yes_cost": 268.372,
      "running_no_cost": 293.2016,
      "running_total_exposure": 561.5736,
      "raw": {
        "proxyWallet": "0x6031b6eed1c97e853c6e0f03ad3ce3529351f96d",
        "asset": "24171791432867916848656083222804673305751745875361756606303355044034777352842",
        "conditionId": "0x920d65638f8b944418e35a41af586cbb01dbbd458dff1ce69a0291c6ef537e89",
        "outcomeIndex": 1
      }
    },
    {
      "trade_number": 96,
      "timestamp": 1765100303,
      "datetime": "2025-12-07 06:38:23",
      "action": "BUY",
      "outcome": "YES",
      "price": 0.33,
      "price_cents": 33.0,
      "shares": 14.0,
      "cost_usd": 4.62,
      "transaction_hash": "0x8287d1fd41c5b6e9112054874b62f7c3a6dc8e4ce7581dd0ebf88b197d7473dd",
      "running_yes_shares": 738.1,
      "running_no_shares": 604.47,
      "running_yes_cost": 272.992,
      "running_no_cost": 293.2016,
      "running_total_exposure": 566.1936,
      "raw": {
        "proxyWallet": "0x6031b6eed1c97e853c6e0f03ad3ce3529351f96d",
        "asset": "91528401740238005717802973551490004353166851233063526555597421997428947532492",
        "conditionId": "0x920d65638f8b944418e35a41af586cbb01dbbd458dff1ce69a0291c6ef537e89",
        "outcomeIndex": 0
      }
    },
    {
      "trade_number": 97,
      "timestamp": 1765100303,
      "datetime": "2025-12-07 06:38:23",
      "action": "BUY",
      "outcome": "YES",
      "price": 0.33,
      "price_cents": 33.0,
      "shares": 14.0,
      "cost_usd": 4.62,
      "transaction_hash": "0x61e2fd439f2038fca31c5f5f37ebb228856c067886bc7dd727c3998d561c9a3e",
      "running_yes_shares": 752.1,
      "running_no_shares": 604.47,
      "running_yes_cost": 277.612,
      "running_no_cost": 293.2016,
      "running_total_exposure": 570.8136,
      "raw": {
        "proxyWallet": "0x6031b6eed1c97e853c6e0f03ad3ce3529351f96d",
        "asset": "91528401740238005717802973551490004353166851233063526555597421997428947532492",
        "conditionId": "0x920d65638f8b944418e35a41af586cbb01dbbd458dff1ce69a0291c6ef537e89",
        "outcomeIndex": 0
      }
    },
    {
      "trade_number": 98,
      "timestamp": 1765100303,
      "datetime": "2025-12-07 06:38:23",
      "action": "BUY",
      "outcome": "YES",
      "price": 0.33,
      "price_cents": 33.0,
      "shares": 14.0,
      "cost_usd": 4.62,
      "transaction_hash": "0xfa63ea5c49398822027dbaac67e720e9d1b9090f24fb61bfccb1ab601db51fda",
      "running_yes_shares": 766.1,
      "running_no_shares": 604.47,
      "running_yes_cost": 282.232,
      "running_no_cost": 293.2016,
      "running_total_exposure": 575.4336,
      "raw": {
        "proxyWallet": "0x6031b6eed1c97e853c6e0f03ad3ce3529351f96d",
        "asset": "91528401740238005717802973551490004353166851233063526555597421997428947532492",
        "conditionId": "0x920d65638f8b944418e35a41af586cbb01dbbd458dff1ce69a0291c6ef537e89",
        "outcomeIndex": 0
      }
    },
    {
      "trade_number": 99,
      "timestamp": 1765100307,
      "datetime": "2025-12-07 06:38:27",
      "action": "BUY",
      "outcome": "NO",
      "price": 0.66,
      "price_cents": 66.0,
      "shares": 14.0,
      "cost_usd": 9.24,
      "transaction_hash": "0x00edb8f7b162722ecdc0a3517d3bdc52831b7187290f4e342305a780a2d85723",
      "running_yes_shares": 766.1,
      "running_no_shares": 618.47,
      "running_yes_cost": 282.232,
      "running_no_cost": 302.4416,
      "running_total_exposure": 584.6736,
      "raw": {
        "proxyWallet": "0x6031b6eed1c97e853c6e0f03ad3ce3529351f96d",
        "asset": "24171791432867916848656083222804673305751745875361756606303355044034777352842",
        "conditionId": "0x920d65638f8b944418e35a41af586cbb01dbbd458dff1ce69a0291c6ef537e89",
        "outcomeIndex": 1
      }
    },
    {
      "trade_number": 100,
      "timestamp": 1765100309,
      "datetime": "2025-12-07 06:38:29",
      "action": "BUY",
      "outcome": "NO",
      "price": 0.66,
      "price_cents": 66.0,
      "shares": 14.0,
      "cost_usd": 9.24,
      "transaction_hash": "0xbe00b3c5aebf086d72279ccff0e9893e02dbb60a656ab5f328392cbd191ef9a8",
      "running_yes_shares": 766.1,
      "running_no_shares": 632.47,
      "running_yes_cost": 282.232,
      "running_no_cost": 311.6816,
      "running_total_exposure": 593.9136,
      "raw": {
        "proxyWallet": "0x6031b6eed1c97e853c6e0f03ad3ce3529351f96d",
        "asset": "24171791432867916848656083222804673305751745875361756606303355044034777352842",
        "conditionId": "0x920d65638f8b944418e35a41af586cbb01dbbd458dff1ce69a0291c6ef537e89",
        "outcomeIndex": 1
      }
    },
    {
      "trade_number": 101,
      "timestamp": 1765100309,
      "datetime": "2025-12-07 06:38:29",
      "action": "BUY",
      "outcome": "NO",
      "price": 0.66,
      "price_cents": 66.0,
      "shares": 14.0,
      "cost_usd": 9.24,
      "transaction_hash": "0x6eca1ed0dc1e11bfb501e39187843ce34c501072c38e3647aceb87f3ffc4d46f",
      "running_yes_shares": 766.1,
      "running_no_shares": 646.47,
      "running_yes_cost": 282.232,
      "running_no_cost": 320.9216,
      "running_total_exposure": 603.1536,
      "raw": {
        "proxyWallet": "0x6031b6eed1c97e853c6e0f03ad3ce3529351f96d",
        "asset": "24171791432867916848656083222804673305751745875361756606303355044034777352842",
        "conditionId": "0x920d65638f8b944418e35a41af586cbb01dbbd458dff1ce69a0291c6ef537e89",
        "outcomeIndex": 1
      }
    },
    {
      "trade_number": 102,
      "timestamp": 1765100309,
      "datetime": "2025-12-07 06:38:29",
      "action": "BUY",
      "outcome": "NO",
      "price": 0.66,
      "price_cents": 66.0,
      "shares": 14.0,
      "cost_usd": 9.24,
      "transaction_hash": "0xb273c98b893a70e44506a15eea436913ee3f394fd600f6dae08ded41870d4233",
      "running_yes_shares": 766.1,
      "running_no_shares": 660.47,
      "running_yes_cost": 282.232,
      "running_no_cost": 330.1616,
      "running_total_exposure": 612.3936,
      "raw": {
        "proxyWallet": "0x6031b6eed1c97e853c6e0f03ad3ce3529351f96d",
        "asset": "24171791432867916848656083222804673305751745875361756606303355044034777352842",
        "conditionId": "0x920d65638f8b944418e35a41af586cbb01dbbd458dff1ce69a0291c6ef537e89",
        "outcomeIndex": 1
      }
    },
    {
      "trade_number": 103,
      "timestamp": 1765100329,
      "datetime": "2025-12-07 06:38:49",
      "action": "BUY",
      "outcome": "YES",
      "price": 0.34,
      "price_cents": 34.0,
      "shares": 14.0,
      "cost_usd": 4.76,
      "transaction_hash": "0x73047f2181dc6b7de5c62950d0a23714ceabb55284e5ebc84a55c0f54506b6bd",
      "running_yes_shares": 780.1,
      "running_no_shares": 660.47,
      "running_yes_cost": 286.992,
      "running_no_cost": 330.1616,
      "running_total_exposure": 617.1536,
      "raw": {
        "proxyWallet": "0x6031b6eed1c97e853c6e0f03ad3ce3529351f96d",
        "asset": "91528401740238005717802973551490004353166851233063526555597421997428947532492",
        "conditionId": "0x920d65638f8b944418e35a41af586cbb01dbbd458dff1ce69a0291c6ef537e89",
        "outcomeIndex": 0
      }
    },
    {
      "trade_number": 104,
      "timestamp": 1765100329,
      "datetime": "2025-12-07 06:38:49",
      "action": "BUY",
      "outcome": "YES",
      "price": 0.34,
      "price_cents": 34.0,
      "shares": 14.0,
      "cost_usd": 4.76,
      "transaction_hash": "0x6a760bbbec0573e159c67a14f630a814760d878f6e1c2a719ed472c4dcce3032",
      "running_yes_shares": 794.1,
      "running_no_shares": 660.47,
      "running_yes_cost": 291.752,
      "running_no_cost": 330.1616,
      "running_total_exposure": 621.9136,
      "raw": {
        "proxyWallet": "0x6031b6eed1c97e853c6e0f03ad3ce3529351f96d",
        "asset": "91528401740238005717802973551490004353166851233063526555597421997428947532492",
        "conditionId": "0x920d65638f8b944418e35a41af586cbb01dbbd458dff1ce69a0291c6ef537e89",
        "outcomeIndex": 0
      }
    },
    {
      "trade_number": 105,
      "timestamp": 1765100329,
      "datetime": "2025-12-07 06:38:49",
      "action": "BUY",
      "outcome": "YES",
      "price": 0.34,
      "price_cents": 34.0,
      "shares": 14.0,
      "cost_usd": 4.76,
      "transaction_hash": "0x2adfbfbde973cd32e2aed9e546a047a7b7e87552c09265d47962b64b25ac4736",
      "running_yes_shares": 808.1,
      "running_no_shares": 660.47,
      "running_yes_cost": 296.512,
      "running_no_cost": 330.1616,
      "running_total_exposure": 626.6736,
      "raw": {
        "proxyWallet": "0x6031b6eed1c97e853c6e0f03ad3ce3529351f96d",
        "asset": "91528401740238005717802973551490004353166851233063526555597421997428947532492",
        "conditionId": "0x920d65638f8b944418e35a41af586cbb01dbbd458dff1ce69a0291c6ef537e89",
        "outcomeIndex": 0
      }
    },
    {
      "trade_number": 106,
      "timestamp": 1765100331,
      "datetime": "2025-12-07 06:38:51",
      "action": "BUY",
      "outcome": "YES",
      "price": 0.34,
      "price_cents": 34.0,
      "shares": 14.0,
      "cost_usd": 4.76,
      "transaction_hash": "0xc024dab77d0c5a91d6aa195cd9b7971dea3d504c56a4d5a0af52c98436c9a856",
      "running_yes_shares": 822.1,
      "running_no_shares": 660.47,
      "running_yes_cost": 301.272,
      "running_no_cost": 330.1616,
      "running_total_exposure": 631.4336,
      "raw": {
        "proxyWallet": "0x6031b6eed1c97e853c6e0f03ad3ce3529351f96d",
        "asset": "91528401740238005717802973551490004353166851233063526555597421997428947532492",
        "conditionId": "0x920d65638f8b944418e35a41af586cbb01dbbd458dff1ce69a0291c6ef537e89",
        "outcomeIndex": 0
      }
    },
    {
      "trade_number": 107,
      "timestamp": 1765100331,
      "datetime": "2025-12-07 06:38:51",
      "action": "BUY",
      "outcome": "YES",
      "price": 0.34,
      "price_cents": 34.0,
      "shares": 14.0,
      "cost_usd": 4.76,
      "transaction_hash": "0xc7573fa86462dd6965d03944b9834310d640df91bc5ede0357d73570aee4a438",
      "running_yes_shares": 836.1,
      "running_no_shares": 660.47,
      "running_yes_cost": 306.032,
      "running_no_cost": 330.1616,
      "running_total_exposure": 636.1936,
      "raw": {
        "proxyWallet": "0x6031b6eed1c97e853c6e0f03ad3ce3529351f96d",
        "asset": "91528401740238005717802973551490004353166851233063526555597421997428947532492",
        "conditionId": "0x920d65638f8b944418e35a41af586cbb01dbbd458dff1ce69a0291c6ef537e89",
        "outcomeIndex": 0
      }
    },
    {
      "trade_number": 108,
      "timestamp": 1765100331,
      "datetime": "2025-12-07 06:38:51",
      "action": "BUY",
      "outcome": "YES",
      "price": 0.34,
      "price_cents": 34.0,
      "shares": 14.0,
      "cost_usd": 4.76,
      "transaction_hash": "0x0108608c66d62a441d91415271734cf3265d3a4085f606d6d15c2da1a7c68cea",
      "running_yes_shares": 850.1,
      "running_no_shares": 660.47,
      "running_yes_cost": 310.792,
      "running_no_cost": 330.1616,
      "running_total_exposure": 640.9536,
      "raw": {
        "proxyWallet": "0x6031b6eed1c97e853c6e0f03ad3ce3529351f96d",
        "asset": "91528401740238005717802973551490004353166851233063526555597421997428947532492",
        "conditionId": "0x920d65638f8b944418e35a41af586cbb01dbbd458dff1ce69a0291c6ef537e89",
        "outcomeIndex": 0
      }
    },
    {
      "trade_number": 109,
      "timestamp": 1765100331,
      "datetime": "2025-12-07 06:38:51",
      "action": "BUY",
      "outcome": "YES",
      "price": 0.34,
      "price_cents": 34.0,
      "shares": 14.0,
      "cost_usd": 4.76,
      "transaction_hash": "0xae2b522b56e1cda7dd9790a606cb94f9dfa41b218e6499a93a1bf15c2c066d4e",
      "running_yes_shares": 864.1,
      "running_no_shares": 660.47,
      "running_yes_cost": 315.552,
      "running_no_cost": 330.1616,
      "running_total_exposure": 645.7136,
      "raw": {
        "proxyWallet": "0x6031b6eed1c97e853c6e0f03ad3ce3529351f96d",
        "asset": "91528401740238005717802973551490004353166851233063526555597421997428947532492",
        "conditionId": "0x920d65638f8b944418e35a41af586cbb01dbbd458dff1ce69a0291c6ef537e89",
        "outcomeIndex": 0
      }
    },
    {
      "trade_number": 110,
      "timestamp": 1765100403,
      "datetime": "2025-12-07 06:40:03",
      "action": "BUY",
      "outcome": "NO",
      "price": 0.77,
      "price_cents": 77.0,
      "shares": 14.0,
      "cost_usd": 10.78,
      "transaction_hash": "0xceadd185fbd9f024ef0a01fdbd70d2280ea4de27769067e9822e7e2161f063e3",
      "running_yes_shares": 864.1,
      "running_no_shares": 674.47,
      "running_yes_cost": 315.552,
      "running_no_cost": 340.9416,
      "running_total_exposure": 656.4936,
      "raw": {
        "proxyWallet": "0x6031b6eed1c97e853c6e0f03ad3ce3529351f96d",
        "asset": "24171791432867916848656083222804673305751745875361756606303355044034777352842",
        "conditionId": "0x920d65638f8b944418e35a41af586cbb01dbbd458dff1ce69a0291c6ef537e89",
        "outcomeIndex": 1
      }
    },
    {
      "trade_number": 111,
      "timestamp": 1765100403,
      "datetime": "2025-12-07 06:40:03",
      "action": "BUY",
      "outcome": "NO",
      "price": 0.77,
      "price_cents": 77.0,
      "shares": 7.0,
      "cost_usd": 5.39,
      "transaction_hash": "0x1e8098cd9b700f130948afce9d83b3f6689e1812d2494ee19b0a34cc0f6226f4",
      "running_yes_shares": 864.1,
      "running_no_shares": 681.47,
      "running_yes_cost": 315.552,
      "running_no_cost": 346.3316,
      "running_total_exposure": 661.8836,
      "raw": {
        "proxyWallet": "0x6031b6eed1c97e853c6e0f03ad3ce3529351f96d",
        "asset": "24171791432867916848656083222804673305751745875361756606303355044034777352842",
        "conditionId": "0x920d65638f8b944418e35a41af586cbb01dbbd458dff1ce69a0291c6ef537e89",
        "outcomeIndex": 1
      }
    },
    {
      "trade_number": 112,
      "timestamp": 1765100405,
      "datetime": "2025-12-07 06:40:05",
      "action": "BUY",
      "outcome": "NO",
      "price": 0.77,
      "price_cents": 77.0,
      "shares": 14.0,
      "cost_usd": 10.78,
      "transaction_hash": "0xfb623c3de414f3f95e0c1eca51dba439eb39387f9ec0bd0e0679415be6f7f982",
      "running_yes_shares": 864.1,
      "running_no_shares": 695.47,
      "running_yes_cost": 315.552,
      "running_no_cost": 357.1116,
      "running_total_exposure": 672.6636,
      "raw": {
        "proxyWallet": "0x6031b6eed1c97e853c6e0f03ad3ce3529351f96d",
        "asset": "24171791432867916848656083222804673305751745875361756606303355044034777352842",
        "conditionId": "0x920d65638f8b944418e35a41af586cbb01dbbd458dff1ce69a0291c6ef537e89",
        "outcomeIndex": 1
      }
    },
    {
      "trade_number": 113,
      "timestamp": 1765100471,
      "datetime": "2025-12-07 06:41:11",
      "action": "BUY",
      "outcome": "NO",
      "price": 0.83,
      "price_cents": 83.0,
      "shares": 10.0,
      "cost_usd": 8.3,
      "transaction_hash": "0x008a5a1f96f844aa420580d124e0b33dda01b82f8e42b53e4071bcfee075dc98",
      "running_yes_shares": 864.1,
      "running_no_shares": 705.47,
      "running_yes_cost": 315.552,
      "running_no_cost": 365.4116,
      "running_total_exposure": 680.9636,
      "raw": {
        "proxyWallet": "0x6031b6eed1c97e853c6e0f03ad3ce3529351f96d",
        "asset": "24171791432867916848656083222804673305751745875361756606303355044034777352842",
        "conditionId": "0x920d65638f8b944418e35a41af586cbb01dbbd458dff1ce69a0291c6ef537e89",
        "outcomeIndex": 1
      }
    },
    {
      "trade_number": 114,
      "timestamp": 1765100473,
      "datetime": "2025-12-07 06:41:13",
      "action": "BUY",
      "outcome": "NO",
      "price": 0.85,
      "price_cents": 85.0,
      "shares": 6.39,
      "cost_usd": 5.4315,
      "transaction_hash": "0x3a6a1db5cbf61067993629d6489bb0d78ae3b784e0a3b41fc9bb09f78e9fcea0",
      "running_yes_shares": 864.1,
      "running_no_shares": 711.86,
      "running_yes_cost": 315.552,
      "running_no_cost": 370.8431,
      "running_total_exposure": 686.3951,
      "raw": {
        "proxyWallet": "0x6031b6eed1c97e853c6e0f03ad3ce3529351f96d",
        "asset": "24171791432867916848656083222804673305751745875361756606303355044034777352842",
        "conditionId": "0x920d65638f8b944418e35a41af586cbb01dbbd458dff1ce69a0291c6ef537e89",
        "outcomeIndex": 1
      }
    },
    {
      "trade_number": 115,
      "timestamp": 1765100473,
      "datetime": "2025-12-07 06:41:13",
      "action": "BUY",
      "outcome": "NO",
      "price": 0.85,
      "price_cents": 85.0,
      "shares": 14.0,
      "cost_usd": 11.9,
      "transaction_hash": "0x3e61c8c4e77f58f9d3b8b08ebe9a2c702c38a51f57647430202a891eccaad671",
      "running_yes_shares": 864.1,
      "running_no_shares": 725.86,
      "running_yes_cost": 315.552,
      "running_no_cost": 382.7431,
      "running_total_exposure": 698.2951,
      "raw": {
        "proxyWallet": "0x6031b6eed1c97e853c6e0f03ad3ce3529351f96d",
        "asset": "24171791432867916848656083222804673305751745875361756606303355044034777352842",
        "conditionId": "0x920d65638f8b944418e35a41af586cbb01dbbd458dff1ce69a0291c6ef537e89",
        "outcomeIndex": 1
      }
    },
    {
      "trade_number": 116,
      "timestamp": 1765100625,
      "datetime": "2025-12-07 06:43:45",
      "action": "BUY",
      "outcome": "YES",
      "price": 0.13,
      "price_cents": 13.0,
      "shares": 5.69,
      "cost_usd": 0.7397,
      "transaction_hash": "0x16bf19a113c84fde27f548b4f641b5d5372db431f4d58e5d4091525e96508465",
      "running_yes_shares": 869.79,
      "running_no_shares": 725.86,
      "running_yes_cost": 316.2917,
      "running_no_cost": 382.7431,
      "running_total_exposure": 699.0348,
      "raw": {
        "proxyWallet": "0x6031b6eed1c97e853c6e0f03ad3ce3529351f96d",
        "asset": "91528401740238005717802973551490004353166851233063526555597421997428947532492",
        "conditionId": "0x920d65638f8b944418e35a41af586cbb01dbbd458dff1ce69a0291c6ef537e89",
        "outcomeIndex": 0
      }
    },
    {
      "trade_number": 117,
      "timestamp": 1765100675,
      "datetime": "2025-12-07 06:44:35",
      "action": "BUY",
      "outcome": "YES",
      "price": 0.09,
      "price_cents": 9.0,
      "shares": 13.0,
      "cost_usd": 1.17,
      "transaction_hash": "0x0e5d83e5741a257643e7bbeec0c5cb462740aee83b4c9f92b9dce7c80b781e28",
      "running_yes_shares": 882.79,
      "running_no_shares": 725.86,
      "running_yes_cost": 317.4617,
      "running_no_cost": 382.7431,
      "running_total_exposure": 700.2048,
      "raw": {
        "proxyWallet": "0x6031b6eed1c97e853c6e0f03ad3ce3529351f96d",
        "asset": "91528401740238005717802973551490004353166851233063526555597421997428947532492",
        "conditionId": "0x920d65638f8b944418e35a41af586cbb01dbbd458dff1ce69a0291c6ef537e89",
        "outcomeIndex": 0
      }
    },
    {
      "trade_number": 118,
      "timestamp": 1765100675,
      "datetime": "2025-12-07 06:44:35",
      "action": "BUY",
      "outcome": "YES",
      "price": 0.09,
      "price_cents": 9.0,
      "shares": 13.0,
      "cost_usd": 1.17,
      "transaction_hash": "0x69c89b659582a5e30cb0286559e06ee1a7866767d5de9cdf4518846ecc8edd85",
      "running_yes_shares": 895.79,
      "running_no_shares": 725.86,
      "running_yes_cost": 318.6317,
      "running_no_cost": 382.7431,
      "running_total_exposure": 701.3748,
      "raw": {
        "proxyWallet": "0x6031b6eed1c97e853c6e0f03ad3ce3529351f96d",
        "asset": "91528401740238005717802973551490004353166851233063526555597421997428947532492",
        "conditionId": "0x920d65638f8b944418e35a41af586cbb01dbbd458dff1ce69a0291c6ef537e89",
        "outcomeIndex": 0
      }
    }
  ]
}