{
  "slug": "ethereum-up-or-down-december-2-9am-et",
  "wallet": "0x6031b6eed1c97e853c6e0f03ad3ce3529351f96d",
  "exported_at": "2025-12-23T12:35:42.744387",
  "summary": {
    "resolution": "YES",
    "total_trades": 33,
    "time_range": {
      "first_trade": "2025-12-02 11:01:08",
      "last_trade": "2025-12-02 11:26:50",
      "first_trade_ts": 1764684068,
      "last_trade_ts": 1764685610
    },
    "final_position": {
      "remaining_yes_shares": 206.94,
      "remaining_no_shares": 115.0
    },
    "costs": {
      "yes_buy_shares": 206.94,
      "yes_buy_cost": 126.0082,
      "yes_sell_shares": 0,
      "yes_sell_cost": 0,
      "no_buy_shares": 115.0,
      "no_buy_cost": 56.65,
      "no_sell_shares": 0,
      "no_sell_cost": 0
    },
    "pnl": {
      "total_spent": 182.6582,
      "final_value": 206.94,
      "pnl": 24.2818,
      "pnl_percent": 13.29
    }
  },
  "trades": [
    {
      "trade_number": 1,
      "timestamp": 1764684068,
      "datetime": "2025-12-02 11:01:08",
      "action": "BUY",
      "outcome": "NO",
      "price": 0.54,
      "price_cents": 54.0,
      "shares": 10.0,
      "cost_usd": 5.4,
      "transaction_hash": "0x043860152e47aa42a2fd1ff3f136860af56d8caee1184266f957d960ac3534c2",
      "running_yes_shares": 0,
      "running_no_shares": 10.0,
      "running_yes_cost": 0,
      "running_no_cost": 5.4,
      "running_total_exposure": 5.4,
      "raw": {
        "proxyWallet": "0x6031b6eed1c97e853c6e0f03ad3ce3529351f96d",
        "asset": "113407036167664785576376789711278614747841678215063757902922971098867035178010",
        "conditionId": "0x948879cbe88cd0772fcad6385739257dbf9794aec6476921aec56946248dfc16",
        "outcomeIndex": 1
      }
    },
    {
      "trade_number": 2,
      "timestamp": 1764684096,
      "datetime": "2025-12-02 11:01:36",
      "action": "BUY",
      "outcome": "YES",
      "price": 0.48,
      "price_cents": 48.0,
      "shares": 10.0,
      "cost_usd": 4.8,
      "transaction_hash": "0x646d33874f358180d0159184904e0b5d2c8d1d26de89ee65c14077abe41748d0",
      "running_yes_shares": 10.0,
      "running_no_shares": 10.0,
      "running_yes_cost": 4.8,
      "running_no_cost": 5.4,
      "running_total_exposure": 10.2,
      "raw": {
        "proxyWallet": "0x6031b6eed1c97e853c6e0f03ad3ce3529351f96d",
        "asset": "87622880792243025840609491071150058941274489300274725752299556139323233062390",
        "conditionId": "0x948879cbe88cd0772fcad6385739257dbf9794aec6476921aec56946248dfc16",
        "outcomeIndex": 0
      }
    },
    {
      "trade_number": 3,
      "timestamp": 1764684096,
      "datetime": "2025-12-02 11:01:36",
      "action": "BUY",
      "outcome": "YES",
      "price": 0.48,
      "price_cents": 48.0,
      "shares": 10.0,
      "cost_usd": 4.8,
      "transaction_hash": "0x1e03e5b2a20de84dc7b57c0a597bbcb604900c22b962086fbe8944947d8a35d0",
      "running_yes_shares": 20.0,
      "running_no_shares": 10.0,
      "running_yes_cost": 9.6,
      "running_no_cost": 5.4,
      "running_total_exposure": 15.0,
      "raw": {
        "proxyWallet": "0x6031b6eed1c97e853c6e0f03ad3ce3529351f96d",
        "asset": "87622880792243025840609491071150058941274489300274725752299556139323233062390",
        "conditionId": "0x948879cbe88cd0772fcad6385739257dbf9794aec6476921aec56946248dfc16",
        "outcomeIndex": 0
      }
    },
    {
      "trade_number": 4,
      "timestamp": 1764684096,
      "datetime": "2025-12-02 11:01:36",
      "action": "BUY",
      "outcome": "YES",
      "price": 0.48,
      "price_cents": 48.0,
      "shares": 10.0,
      "cost_usd": 4.8,
      "transaction_hash": "0x7017fc5a6fc02bc70dc54b2816bd815db0b5aed21bcf644ffb3b2792f7e1ae8c",
      "running_yes_shares": 30.0,
      "running_no_shares": 10.0,
      "running_yes_cost": 14.4,
      "running_no_cost": 5.4,
      "running_total_exposure": 19.8,
      "raw": {
        "proxyWallet": "0x6031b6eed1c97e853c6e0f03ad3ce3529351f96d",
        "asset": "87622880792243025840609491071150058941274489300274725752299556139323233062390",
        "conditionId": "0x948879cbe88cd0772fcad6385739257dbf9794aec6476921aec56946248dfc16",
        "outcomeIndex": 0
      }
    },
    {
      "trade_number": 5,
      "timestamp": 1764684096,
      "datetime": "2025-12-02 11:01:36",
      "action": "BUY",
      "outcome": "YES",
      "price": 0.48,
      "price_cents": 48.0,
      "shares": 10.0,
      "cost_usd": 4.8,
      "transaction_hash": "0x5ff1a4288f76b5691c6de939d7d88a0d7194a6948516551da598df30dc02854b",
      "running_yes_shares": 40.0,
      "running_no_shares": 10.0,
      "running_yes_cost": 19.2,
      "running_no_cost": 5.4,
      "running_total_exposure": 24.6,
      "raw": {
        "proxyWallet": "0x6031b6eed1c97e853c6e0f03ad3ce3529351f96d",
        "asset": "87622880792243025840609491071150058941274489300274725752299556139323233062390",
        "conditionId": "0x948879cbe88cd0772fcad6385739257dbf9794aec6476921aec56946248dfc16",
        "outcomeIndex": 0
      }
    },
    {
      "trade_number": 6,
      "timestamp": 1764684126,
      "datetime": "2025-12-02 11:02:06",
      "action": "BUY",
      "outcome": "NO",
      "price": 0.52,
      "price_cents": 52.0,
      "shares": 10.0,
      "cost_usd": 5.2,
      "transaction_hash": "0x486ad81bf2f275d86ad0f1cd52bd4bf8c48755c01c2f432355587377e378587e",
      "running_yes_shares": 40.0,
      "running_no_shares": 20.0,
      "running_yes_cost": 19.2,
      "running_no_cost": 10.6,
      "running_total_exposure": 29.8,
      "raw": {
        "proxyWallet": "0x6031b6eed1c97e853c6e0f03ad3ce3529351f96d",
        "asset": "113407036167664785576376789711278614747841678215063757902922971098867035178010",
        "conditionId": "0x948879cbe88cd0772fcad6385739257dbf9794aec6476921aec56946248dfc16",
        "outcomeIndex": 1
      }
    },
    {
      "trade_number": 7,
      "timestamp": 1764684126,
      "datetime": "2025-12-02 11:02:06",
      "action": "BUY",
      "outcome": "NO",
      "price": 0.52,
      "price_cents": 52.0,
      "shares": 10.0,
      "cost_usd": 5.2,
      "transaction_hash": "0x266fdd6a671534fb2ea06d1eefc6f2d8f9118939c4e57a3de106162d1acd5c19",
      "running_yes_shares": 40.0,
      "running_no_shares": 30.0,
      "running_yes_cost": 19.2,
      "running_no_cost": 15.8,
      "running_total_exposure": 35.0,
      "raw": {
        "proxyWallet": "0x6031b6eed1c97e853c6e0f03ad3ce3529351f96d",
        "asset": "113407036167664785576376789711278614747841678215063757902922971098867035178010",
        "conditionId": "0x948879cbe88cd0772fcad6385739257dbf9794aec6476921aec56946248dfc16",
        "outcomeIndex": 1
      }
    },
    {
      "trade_number": 8,
      "timestamp": 1764684148,
      "datetime": "2025-12-02 11:02:28",
      "action": "BUY",
      "outcome": "YES",
      "price": 0.44,
      "price_cents": 44.0,
      "shares": 8.0,
      "cost_usd": 3.52,
      "transaction_hash": "0x99e1e6be5cc4bff702f61519d180da229b0ecfa29e1166d8e30d6cc566b38887",
      "running_yes_shares": 48.0,
      "running_no_shares": 30.0,
      "running_yes_cost": 22.72,
      "running_no_cost": 15.8,
      "running_total_exposure": 38.52,
      "raw": {
        "proxyWallet": "0x6031b6eed1c97e853c6e0f03ad3ce3529351f96d",
        "asset": "87622880792243025840609491071150058941274489300274725752299556139323233062390",
        "conditionId": "0x948879cbe88cd0772fcad6385739257dbf9794aec6476921aec56946248dfc16",
        "outcomeIndex": 0
      }
    },
    {
      "trade_number": 9,
      "timestamp": 1764684298,
      "datetime": "2025-12-02 11:04:58",
      "action": "BUY",
      "outcome": "NO",
      "price": 0.52,
      "price_cents": 52.0,
      "shares": 10.0,
      "cost_usd": 5.2,
      "transaction_hash": "0xdca8a937f13c22e63092a67de8dab1d36970d7f32cdeb311d78e56822453cfda",
      "running_yes_shares": 48.0,
      "running_no_shares": 40.0,
      "running_yes_cost": 22.72,
      "running_no_cost": 21.0,
      "running_total_exposure": 43.72,
      "raw": {
        "proxyWallet": "0x6031b6eed1c97e853c6e0f03ad3ce3529351f96d",
        "asset": "113407036167664785576376789711278614747841678215063757902922971098867035178010",
        "conditionId": "0x948879cbe88cd0772fcad6385739257dbf9794aec6476921aec56946248dfc16",
        "outcomeIndex": 1
      }
    },
    {
      "trade_number": 10,
      "timestamp": 1764684300,
      "datetime": "2025-12-02 11:05:00",
      "action": "BUY",
      "outcome": "NO",
      "price": 0.52,
      "price_cents": 52.0,
      "shares": 10.0,
      "cost_usd": 5.2,
      "transaction_hash": "0x069785361d082206e5e2c3f22fbe850b43b42a27c94756b0ae3906acd6391d5f",
      "running_yes_shares": 48.0,
      "running_no_shares": 50.0,
      "running_yes_cost": 22.72,
      "running_no_cost": 26.2,
      "running_total_exposure": 48.92,
      "raw": {
        "proxyWallet": "0x6031b6eed1c97e853c6e0f03ad3ce3529351f96d",
        "asset": "113407036167664785576376789711278614747841678215063757902922971098867035178010",
        "conditionId": "0x948879cbe88cd0772fcad6385739257dbf9794aec6476921aec56946248dfc16",
        "outcomeIndex": 1
      }
    },
    {
      "trade_number": 11,
      "timestamp": 1764684302,
      "datetime": "2025-12-02 11:05:02",
      "action": "BUY",
      "outcome": "NO",
      "price": 0.52,
      "price_cents": 52.0,
      "shares": 10.0,
      "cost_usd": 5.2,
      "transaction_hash": "0xed9d61bfc2a7defd323692f27d8eecb663ebdcee477b50b3e17c37dc144bd458",
      "running_yes_shares": 48.0,
      "running_no_shares": 60.0,
      "running_yes_cost": 22.72,
      "running_no_cost": 31.4,
      "running_total_exposure": 54.12,
      "raw": {
        "proxyWallet": "0x6031b6eed1c97e853c6e0f03ad3ce3529351f96d",
        "asset": "113407036167664785576376789711278614747841678215063757902922971098867035178010",
        "conditionId": "0x948879cbe88cd0772fcad6385739257dbf9794aec6476921aec56946248dfc16",
        "outcomeIndex": 1
      }
    },
    {
      "trade_number": 12,
      "timestamp": 1764684302,
      "datetime": "2025-12-02 11:05:02",
      "action": "BUY",
      "outcome": "NO",
      "price": 0.52,
      "price_cents": 52.0,
      "shares": 10.0,
      "cost_usd": 5.2,
      "transaction_hash": "0x2499c8e177fb831f409c39ce2564faf72067425c1a8198037314149e1483ba11",
      "running_yes_shares": 48.0,
      "running_no_shares": 70.0,
      "running_yes_cost": 22.72,
      "running_no_cost": 36.6,
      "running_total_exposure": 59.32,
      "raw": {
        "proxyWallet": "0x6031b6eed1c97e853c6e0f03ad3ce3529351f96d",
        "asset": "113407036167664785576376789711278614747841678215063757902922971098867035178010",
        "conditionId": "0x948879cbe88cd0772fcad6385739257dbf9794aec6476921aec56946248dfc16",
        "outcomeIndex": 1
      }
    },
    {
      "trade_number": 13,
      "timestamp": 1764684314,
      "datetime": "2025-12-02 11:05:14",
      "action": "BUY",
      "outcome": "YES",
      "price": 0.49,
      "price_cents": 49.0,
      "shares": 10.0,
      "cost_usd": 4.9,
      "transaction_hash": "0x54d7394f184c190a39801add99b6713a551d9f64468fb99fed22e42e17a7ffec",
      "running_yes_shares": 58.0,
      "running_no_shares": 70.0,
      "running_yes_cost": 27.62,
      "running_no_cost": 36.6,
      "running_total_exposure": 64.22,
      "raw": {
        "proxyWallet": "0x6031b6eed1c97e853c6e0f03ad3ce3529351f96d",
        "asset": "87622880792243025840609491071150058941274489300274725752299556139323233062390",
        "conditionId": "0x948879cbe88cd0772fcad6385739257dbf9794aec6476921aec56946248dfc16",
        "outcomeIndex": 0
      }
    },
    {
      "trade_number": 14,
      "timestamp": 1764684318,
      "datetime": "2025-12-02 11:05:18",
      "action": "BUY",
      "outcome": "NO",
      "price": 0.51,
      "price_cents": 51.0,
      "shares": 10.0,
      "cost_usd": 5.1,
      "transaction_hash": "0x9c204ddd45b44f30579be53b6b6116920c48638ec5da17690fbb87273e3c5d2c",
      "running_yes_shares": 58.0,
      "running_no_shares": 80.0,
      "running_yes_cost": 27.62,
      "running_no_cost": 41.7,
      "running_total_exposure": 69.32,
      "raw": {
        "proxyWallet": "0x6031b6eed1c97e853c6e0f03ad3ce3529351f96d",
        "asset": "113407036167664785576376789711278614747841678215063757902922971098867035178010",
        "conditionId": "0x948879cbe88cd0772fcad6385739257dbf9794aec6476921aec56946248dfc16",
        "outcomeIndex": 1
      }
    },
    {
      "trade_number": 15,
      "timestamp": 1764684318,
      "datetime": "2025-12-02 11:05:18",
      "action": "BUY",
      "outcome": "NO",
      "price": 0.51,
      "price_cents": 51.0,
      "shares": 10.0,
      "cost_usd": 5.1,
      "transaction_hash": "0x5fc1d26abd7cb8a90050644e0103aa5b1aa7555663de88d2246d9b56463d02f2",
      "running_yes_shares": 58.0,
      "running_no_shares": 90.0,
      "running_yes_cost": 27.62,
      "running_no_cost": 46.8,
      "running_total_exposure": 74.42,
      "raw": {
        "proxyWallet": "0x6031b6eed1c97e853c6e0f03ad3ce3529351f96d",
        "asset": "113407036167664785576376789711278614747841678215063757902922971098867035178010",
        "conditionId": "0x948879cbe88cd0772fcad6385739257dbf9794aec6476921aec56946248dfc16",
        "outcomeIndex": 1
      }
    },
    {
      "trade_number": 16,
      "timestamp": 1764684320,
      "datetime": "2025-12-02 11:05:20",
      "action": "BUY",
      "outcome": "NO",
      "price": 0.51,
      "price_cents": 51.0,
      "shares": 10.0,
      "cost_usd": 5.1,
      "transaction_hash": "0x81d5f9dab912b00eb1cdfa5d4738e4ceecd8c344d81958779f996e29886cd579",
      "running_yes_shares": 58.0,
      "running_no_shares": 100.0,
      "running_yes_cost": 27.62,
      "running_no_cost": 51.9,
      "running_total_exposure": 79.52,
      "raw": {
        "proxyWallet": "0x6031b6eed1c97e853c6e0f03ad3ce3529351f96d",
        "asset": "113407036167664785576376789711278614747841678215063757902922971098867035178010",
        "conditionId": "0x948879cbe88cd0772fcad6385739257dbf9794aec6476921aec56946248dfc16",
        "outcomeIndex": 1
      }
    },
    {
      "trade_number": 17,
      "timestamp": 1764684358,
      "datetime": "2025-12-02 11:05:58",
      "action": "BUY",
      "outcome": "YES",
      "price": 0.51,
      "price_cents": 51.0,
      "shares": 10.0,
      "cost_usd": 5.1,
      "transaction_hash": "0x6172bb625ea2f302f41183eb430e98f7119ea690d778ba4c6187508bf57e7afc",
      "running_yes_shares": 68.0,
      "running_no_shares": 100.0,
      "running_yes_cost": 32.72,
      "running_no_cost": 51.9,
      "running_total_exposure": 84.62,
      "raw": {
        "proxyWallet": "0x6031b6eed1c97e853c6e0f03ad3ce3529351f96d",
        "asset": "87622880792243025840609491071150058941274489300274725752299556139323233062390",
        "conditionId": "0x948879cbe88cd0772fcad6385739257dbf9794aec6476921aec56946248dfc16",
        "outcomeIndex": 0
      }
    },
    {
      "trade_number": 18,
      "timestamp": 1764684358,
      "datetime": "2025-12-02 11:05:58",
      "action": "BUY",
      "outcome": "YES",
      "price": 0.51,
      "price_cents": 51.0,
      "shares": 10.0,
      "cost_usd": 5.1,
      "transaction_hash": "0x9fb28d214d577d56834897500045a61931d410b6c1b973aac8d09aac8878ccae",
      "running_yes_shares": 78.0,
      "running_no_shares": 100.0,
      "running_yes_cost": 37.82,
      "running_no_cost": 51.9,
      "running_total_exposure": 89.72,
      "raw": {
        "proxyWallet": "0x6031b6eed1c97e853c6e0f03ad3ce3529351f96d",
        "asset": "87622880792243025840609491071150058941274489300274725752299556139323233062390",
        "conditionId": "0x948879cbe88cd0772fcad6385739257dbf9794aec6476921aec56946248dfc16",
        "outcomeIndex": 0
      }
    },
    {
      "trade_number": 19,
      "timestamp": 1764684358,
      "datetime": "2025-12-02 11:05:58",
      "action": "BUY",
      "outcome": "YES",
      "price": 0.51,
      "price_cents": 51.0,
      "shares": 10.0,
      "cost_usd": 5.1,
      "transaction_hash": "0x8c00dae97788c17baf582020ead8620d99cb805909fce643ba743a5450fe37b7",
      "running_yes_shares": 88.0,
      "running_no_shares": 100.0,
      "running_yes_cost": 42.92,
      "running_no_cost": 51.9,
      "running_total_exposure": 94.82,
      "raw": {
        "proxyWallet": "0x6031b6eed1c97e853c6e0f03ad3ce3529351f96d",
        "asset": "87622880792243025840609491071150058941274489300274725752299556139323233062390",
        "conditionId": "0x948879cbe88cd0772fcad6385739257dbf9794aec6476921aec56946248dfc16",
        "outcomeIndex": 0
      }
    },
    {
      "trade_number": 20,
      "timestamp": 1764684360,
      "datetime": "2025-12-02 11:06:00",
      "action": "BUY",
      "outcome": "YES",
      "price": 0.51,
      "price_cents": 51.0,
      "shares": 10.0,
      "cost_usd": 5.1,
      "transaction_hash": "0xc35803420cefb0ac5016cf2780b67b5e65d3a386f0e0343a8bdbf3328c0a15e5",
      "running_yes_shares": 98.0,
      "running_no_shares": 100.0,
      "running_yes_cost": 48.02,
      "running_no_cost": 51.9,
      "running_total_exposure": 99.92,
      "raw": {
        "proxyWallet": "0x6031b6eed1c97e853c6e0f03ad3ce3529351f96d",
        "asset": "87622880792243025840609491071150058941274489300274725752299556139323233062390",
        "conditionId": "0x948879cbe88cd0772fcad6385739257dbf9794aec6476921aec56946248dfc16",
        "outcomeIndex": 0
      }
    },
    {
      "trade_number": 21,
      "timestamp": 1764684492,
      "datetime": "2025-12-02 11:08:12",
      "action": "BUY",
      "outcome": "YES",
      "price": 0.69,
      "price_cents": 69.0,
      "shares": 10.0,
      "cost_usd": 6.9,
      "transaction_hash": "0x937885114f018b146428f03dae4c4f9428f13742381c9206c8b645e0f36f90cb",
      "running_yes_shares": 108.0,
      "running_no_shares": 100.0,
      "running_yes_cost": 54.92,
      "running_no_cost": 51.9,
      "running_total_exposure": 106.82,
      "raw": {
        "proxyWallet": "0x6031b6eed1c97e853c6e0f03ad3ce3529351f96d",
        "asset": "87622880792243025840609491071150058941274489300274725752299556139323233062390",
        "conditionId": "0x948879cbe88cd0772fcad6385739257dbf9794aec6476921aec56946248dfc16",
        "outcomeIndex": 0
      }
    },
    {
      "trade_number": 22,
      "timestamp": 1764684492,
      "datetime": "2025-12-02 11:08:12",
      "action": "BUY",
      "outcome": "YES",
      "price": 0.69,
      "price_cents": 69.0,
      "shares": 10.0,
      "cost_usd": 6.9,
      "transaction_hash": "0x119a07f7d181feba4fe5b64e409c3f669c510230f2dcb1ff92bc3e393e980f87",
      "running_yes_shares": 118.0,
      "running_no_shares": 100.0,
      "running_yes_cost": 61.82,
      "running_no_cost": 51.9,
      "running_total_exposure": 113.72,
      "raw": {
        "proxyWallet": "0x6031b6eed1c97e853c6e0f03ad3ce3529351f96d",
        "asset": "87622880792243025840609491071150058941274489300274725752299556139323233062390",
        "conditionId": "0x948879cbe88cd0772fcad6385739257dbf9794aec6476921aec56946248dfc16",
        "outcomeIndex": 0
      }
    },
    {
      "trade_number": 23,
      "timestamp": 1764684492,
      "datetime": "2025-12-02 11:08:12",
      "action": "BUY",
      "outcome": "YES",
      "price": 0.6971,
      "price_cents": 69.71,
      "shares": 10.0,
      "cost_usd": 6.9712,
      "transaction_hash": "0x91239678dfcb961bef97370c266f62b54c480e1e2d750514176bb92c6f0030c0",
      "running_yes_shares": 128.0,
      "running_no_shares": 100.0,
      "running_yes_cost": 68.7912,
      "running_no_cost": 51.9,
      "running_total_exposure": 120.6912,
      "raw": {
        "proxyWallet": "0x6031b6eed1c97e853c6e0f03ad3ce3529351f96d",
        "asset": "87622880792243025840609491071150058941274489300274725752299556139323233062390",
        "conditionId": "0x948879cbe88cd0772fcad6385739257dbf9794aec6476921aec56946248dfc16",
        "outcomeIndex": 0
      }
    },
    {
      "trade_number": 24,
      "timestamp": 1764684492,
      "datetime": "2025-12-02 11:08:12",
      "action": "BUY",
      "outcome": "YES",
      "price": 0.69,
      "price_cents": 69.0,
      "shares": 10.0,
      "cost_usd": 6.9,
      "transaction_hash": "0xb7db8394911de2cecf32cd940cda313956c27561b3872688154cd84806d3bc62",
      "running_yes_shares": 138.0,
      "running_no_shares": 100.0,
      "running_yes_cost": 75.6912,
      "running_no_cost": 51.9,
      "running_total_exposure": 127.5912,
      "raw": {
        "proxyWallet": "0x6031b6eed1c97e853c6e0f03ad3ce3529351f96d",
        "asset": "87622880792243025840609491071150058941274489300274725752299556139323233062390",
        "conditionId": "0x948879cbe88cd0772fcad6385739257dbf9794aec6476921aec56946248dfc16",
        "outcomeIndex": 0
      }
    },
    {
      "trade_number": 25,
      "timestamp": 1764684492,
      "datetime": "2025-12-02 11:08:12",
      "action": "BUY",
      "outcome": "YES",
      "price": 0.69,
      "price_cents": 69.0,
      "shares": 10.0,
      "cost_usd": 6.9,
      "transaction_hash": "0x6f2eeba61c24847ffa9c68aa8433595f62380eea3d910a9508dc21bcad2433d0",
      "running_yes_shares": 148.0,
      "running_no_shares": 100.0,
      "running_yes_cost": 82.5912,
      "running_no_cost": 51.9,
      "running_total_exposure": 134.4912,
      "raw": {
        "proxyWallet": "0x6031b6eed1c97e853c6e0f03ad3ce3529351f96d",
        "asset": "87622880792243025840609491071150058941274489300274725752299556139323233062390",
        "conditionId": "0x948879cbe88cd0772fcad6385739257dbf9794aec6476921aec56946248dfc16",
        "outcomeIndex": 0
      }
    },
    {
      "trade_number": 26,
      "timestamp": 1764684502,
      "datetime": "2025-12-02 11:08:22",
      "action": "BUY",
      "outcome": "NO",
      "price": 0.28,
      "price_cents": 28.0,
      "shares": 10.0,
      "cost_usd": 2.8,
      "transaction_hash": "0x652342ea4528a9232b8ec5b3ab9ed9c4312d9cbc61ef72da7ef577484424568d",
      "running_yes_shares": 148.0,
      "running_no_shares": 110.0,
      "running_yes_cost": 82.5912,
      "running_no_cost": 54.7,
      "running_total_exposure": 137.2912,
      "raw": {
        "proxyWallet": "0x6031b6eed1c97e853c6e0f03ad3ce3529351f96d",
        "asset": "113407036167664785576376789711278614747841678215063757902922971098867035178010",
        "conditionId": "0x948879cbe88cd0772fcad6385739257dbf9794aec6476921aec56946248dfc16",
        "outcomeIndex": 1
      }
    },
    {
      "trade_number": 27,
      "timestamp": 1764684518,
      "datetime": "2025-12-02 11:08:38",
      "action": "BUY",
      "outcome": "YES",
      "price": 0.75,
      "price_cents": 75.0,
      "shares": 10.0,
      "cost_usd": 7.5,
      "transaction_hash": "0x0e6cda4e1742b80806754c69370c1f982005b6cbe9cb8058e908a611707cd742",
      "running_yes_shares": 158.0,
      "running_no_shares": 110.0,
      "running_yes_cost": 90.0912,
      "running_no_cost": 54.7,
      "running_total_exposure": 144.7912,
      "raw": {
        "proxyWallet": "0x6031b6eed1c97e853c6e0f03ad3ce3529351f96d",
        "asset": "87622880792243025840609491071150058941274489300274725752299556139323233062390",
        "conditionId": "0x948879cbe88cd0772fcad6385739257dbf9794aec6476921aec56946248dfc16",
        "outcomeIndex": 0
      }
    },
    {
      "trade_number": 28,
      "timestamp": 1764685246,
      "datetime": "2025-12-02 11:20:46",
      "action": "BUY",
      "outcome": "NO",
      "price": 0.39,
      "price_cents": 39.0,
      "shares": 5.0,
      "cost_usd": 1.95,
      "transaction_hash": "0xa4f5f33b39fdfa5b98dec9f805c4fedfe48c16397f3e6471ac00a12c63e12857",
      "running_yes_shares": 158.0,
      "running_no_shares": 115.0,
      "running_yes_cost": 90.0912,
      "running_no_cost": 56.65,
      "running_total_exposure": 146.7412,
      "raw": {
        "proxyWallet": "0x6031b6eed1c97e853c6e0f03ad3ce3529351f96d",
        "asset": "113407036167664785576376789711278614747841678215063757902922971098867035178010",
        "conditionId": "0x948879cbe88cd0772fcad6385739257dbf9794aec6476921aec56946248dfc16",
        "outcomeIndex": 1
      }
    },
    {
      "trade_number": 29,
      "timestamp": 1764685334,
      "datetime": "2025-12-02 11:22:14",
      "action": "BUY",
      "outcome": "YES",
      "price": 0.55,
      "price_cents": 55.0,
      "shares": 8.94,
      "cost_usd": 4.917,
      "transaction_hash": "0x0f41e45034cbd507eb0f7d4e2e332e4b097e844e3e4f07e289ed3e5e22dc0098",
      "running_yes_shares": 166.94,
      "running_no_shares": 115.0,
      "running_yes_cost": 95.0082,
      "running_no_cost": 56.65,
      "running_total_exposure": 151.6582,
      "raw": {
        "proxyWallet": "0x6031b6eed1c97e853c6e0f03ad3ce3529351f96d",
        "asset": "87622880792243025840609491071150058941274489300274725752299556139323233062390",
        "conditionId": "0x948879cbe88cd0772fcad6385739257dbf9794aec6476921aec56946248dfc16",
        "outcomeIndex": 0
      }
    },
    {
      "trade_number": 30,
      "timestamp": 1764685584,
      "datetime": "2025-12-02 11:26:24",
      "action": "BUY",
      "outcome": "YES",
      "price": 0.77,
      "price_cents": 77.0,
      "shares": 10.0,
      "cost_usd": 7.7,
      "transaction_hash": "0x266b511581670a87ebf2d9a86ab19f8230fadcd267f0158a5ceb86327777765b",
      "running_yes_shares": 176.94,
      "running_no_shares": 115.0,
      "running_yes_cost": 102.7082,
      "running_no_cost": 56.65,
      "running_total_exposure": 159.3582,
      "raw": {
        "proxyWallet": "0x6031b6eed1c97e853c6e0f03ad3ce3529351f96d",
        "asset": "87622880792243025840609491071150058941274489300274725752299556139323233062390",
        "conditionId": "0x948879cbe88cd0772fcad6385739257dbf9794aec6476921aec56946248dfc16",
        "outcomeIndex": 0
      }
    },
    {
      "trade_number": 31,
      "timestamp": 1764685584,
      "datetime": "2025-12-02 11:26:24",
      "action": "BUY",
      "outcome": "YES",
      "price": 0.77,
      "price_cents": 77.0,
      "shares": 10.0,
      "cost_usd": 7.7,
      "transaction_hash": "0x2b84faebf9b6d4fc5f608a61ae46ed385a15bbc6fb5b91016ba0fe50d6da7686",
      "running_yes_shares": 186.94,
      "running_no_shares": 115.0,
      "running_yes_cost": 110.4082,
      "running_no_cost": 56.65,
      "running_total_exposure": 167.0582,
      "raw": {
        "proxyWallet": "0x6031b6eed1c97e853c6e0f03ad3ce3529351f96d",
        "asset": "87622880792243025840609491071150058941274489300274725752299556139323233062390",
        "conditionId": "0x948879cbe88cd0772fcad6385739257dbf9794aec6476921aec56946248dfc16",
        "outcomeIndex": 0
      }
    },
    {
      "trade_number": 32,
      "timestamp": 1764685584,
      "datetime": "2025-12-02 11:26:24",
      "action": "BUY",
      "outcome": "YES",
      "price": 0.77,
      "price_cents": 77.0,
      "shares": 10.0,
      "cost_usd": 7.7,
      "transaction_hash": "0x5ba199096aeb9243a92c66ce490d946fa553351e624be0bdb05ecac7c49b8e2e",
      "running_yes_shares": 196.94,
      "running_no_shares": 115.0,
      "running_yes_cost": 118.1082,
      "running_no_cost": 56.65,
      "running_total_exposure": 174.7582,
      "raw": {
        "proxyWallet": "0x6031b6eed1c97e853c6e0f03ad3ce3529351f96d",
        "asset": "87622880792243025840609491071150058941274489300274725752299556139323233062390",
        "conditionId": "0x948879cbe88cd0772fcad6385739257dbf9794aec6476921aec56946248dfc16",
        "outcomeIndex": 0
      }
    },
    {
      "trade_number": 33,
      "timestamp": 1764685610,
      "datetime": "2025-12-02 11:26:50",
      "action": "BUY",
      "outcome": "YES",
      "price": 0.79,
      "price_cents": 79.0,
      "shares": 10.0,
      "cost_usd": 7.9,
      "transaction_hash": "0xd07c0c3400ae3b3c343f0b4c5667d7eb2643aad971c09cebb95d213b4bb32294",
      "running_yes_shares": 206.94,
      "running_no_shares": 115.0,
      "running_yes_cost": 126.0082,
      "running_no_cost": 56.65,
      "running_total_exposure": 182.6582,
      "raw": {
        "proxyWallet": "0x6031b6eed1c97e853c6e0f03ad3ce3529351f96d",
        "asset": "87622880792243025840609491071150058941274489300274725752299556139323233062390",
        "conditionId": "0x948879cbe88cd0772fcad6385739257dbf9794aec6476921aec56946248dfc16",
        "outcomeIndex": 0
      }
    }
  ]
}