{
  "slug": "btc-updown-15m-1766267100",
  "wallet": "0x6031b6eed1c97e853c6e0f03ad3ce3529351f96d",
  "exported_at": "2025-12-23T12:30:34.181241",
  "summary": {
    "resolution": "NO",
    "total_trades": 46,
    "time_range": {
      "first_trade": "2025-12-20 18:45:27",
      "last_trade": "2025-12-20 18:50:07",
      "first_trade_ts": 1766267127,
      "last_trade_ts": 1766267407
    },
    "final_position": {
      "remaining_yes_shares": 400.96,
      "remaining_no_shares": 316.38
    },
    "costs": {
      "yes_buy_shares": 400.96,
      "yes_buy_cost": 131.0696,
      "yes_sell_shares": 0,
      "yes_sell_cost": 0,
      "no_buy_shares": 316.38,
      "no_buy_cost": 197.14,
      "no_sell_shares": 0,
      "no_sell_cost": 0
    },
    "pnl": {
      "total_spent": 328.2096,
      "final_value": 316.38,
      "pnl": -11.8296,
      "pnl_percent": -3.6
    }
  },
  "trades": [
    {
      "trade_number": 1,
      "timestamp": 1766267127,
      "datetime": "2025-12-20 18:45:27",
      "action": "BUY",
      "outcome": "NO",
      "price": 0.5,
      "price_cents": 50.0,
      "shares": 20.0,
      "cost_usd": 10.0,
      "transaction_hash": "0x349304a1db678eacb4876d565d2c61b24a19d5df17318147c8445f0f6ca238c5",
      "running_yes_shares": 0,
      "running_no_shares": 20.0,
      "running_yes_cost": 0,
      "running_no_cost": 10.0,
      "running_total_exposure": 10.0,
      "raw": {
        "proxyWallet": "0x6031b6eed1c97e853c6e0f03ad3ce3529351f96d",
        "asset": "105393520734003569337205125847550967785785535636278335570879470805053456059467",
        "conditionId": "0xf135c3d2b69fdbe31faa6ee7b6392b76921cbf1de349c9a254b671f5549e7ae8",
        "outcomeIndex": 1
      }
    },
    {
      "trade_number": 2,
      "timestamp": 1766267127,
      "datetime": "2025-12-20 18:45:27",
      "action": "BUY",
      "outcome": "NO",
      "price": 0.5,
      "price_cents": 50.0,
      "shares": 20.0,
      "cost_usd": 10.0,
      "transaction_hash": "0x1b429c549d18af11dd8b3a2234d1703392089bda5d1da5891ed0250474f9c2c0",
      "running_yes_shares": 0,
      "running_no_shares": 40.0,
      "running_yes_cost": 0,
      "running_no_cost": 20.0,
      "running_total_exposure": 20.0,
      "raw": {
        "proxyWallet": "0x6031b6eed1c97e853c6e0f03ad3ce3529351f96d",
        "asset": "105393520734003569337205125847550967785785535636278335570879470805053456059467",
        "conditionId": "0xf135c3d2b69fdbe31faa6ee7b6392b76921cbf1de349c9a254b671f5549e7ae8",
        "outcomeIndex": 1
      }
    },
    {
      "trade_number": 3,
      "timestamp": 1766267127,
      "datetime": "2025-12-20 18:45:27",
      "action": "BUY",
      "outcome": "NO",
      "price": 0.5,
      "price_cents": 50.0,
      "shares": 20.0,
      "cost_usd": 10.0,
      "transaction_hash": "0x0137e763e1ff4521c73d9664a269964a5dbb737adc080e56ac7650e5d73e6a26",
      "running_yes_shares": 0,
      "running_no_shares": 60.0,
      "running_yes_cost": 0,
      "running_no_cost": 30.0,
      "running_total_exposure": 30.0,
      "raw": {
        "proxyWallet": "0x6031b6eed1c97e853c6e0f03ad3ce3529351f96d",
        "asset": "105393520734003569337205125847550967785785535636278335570879470805053456059467",
        "conditionId": "0xf135c3d2b69fdbe31faa6ee7b6392b76921cbf1de349c9a254b671f5549e7ae8",
        "outcomeIndex": 1
      }
    },
    {
      "trade_number": 4,
      "timestamp": 1766267157,
      "datetime": "2025-12-20 18:45:57",
      "action": "BUY",
      "outcome": "NO",
      "price": 0.5,
      "price_cents": 50.0,
      "shares": 7.88,
      "cost_usd": 3.94,
      "transaction_hash": "0x91e0ca2327112096cfc2c4915ede5e53b14f96a71acd18392184207167fd893f",
      "running_yes_shares": 0,
      "running_no_shares": 67.88,
      "running_yes_cost": 0,
      "running_no_cost": 33.94,
      "running_total_exposure": 33.94,
      "raw": {
        "proxyWallet": "0x6031b6eed1c97e853c6e0f03ad3ce3529351f96d",
        "asset": "105393520734003569337205125847550967785785535636278335570879470805053456059467",
        "conditionId": "0xf135c3d2b69fdbe31faa6ee7b6392b76921cbf1de349c9a254b671f5549e7ae8",
        "outcomeIndex": 1
      }
    },
    {
      "trade_number": 5,
      "timestamp": 1766267159,
      "datetime": "2025-12-20 18:45:59",
      "action": "BUY",
      "outcome": "YES",
      "price": 0.51,
      "price_cents": 51.0,
      "shares": 20.0,
      "cost_usd": 10.2,
      "transaction_hash": "0x34035b4d9ac3b379b23ef6291ec8f62a611f7b80a1db5c1a7d764554081bd47d",
      "running_yes_shares": 20.0,
      "running_no_shares": 67.88,
      "running_yes_cost": 10.2,
      "running_no_cost": 33.94,
      "running_total_exposure": 44.14,
      "raw": {
        "proxyWallet": "0x6031b6eed1c97e853c6e0f03ad3ce3529351f96d",
        "asset": "22937902771157015749883661291284904936746607727282925886170992544903461006916",
        "conditionId": "0xf135c3d2b69fdbe31faa6ee7b6392b76921cbf1de349c9a254b671f5549e7ae8",
        "outcomeIndex": 0
      }
    },
    {
      "trade_number": 6,
      "timestamp": 1766267159,
      "datetime": "2025-12-20 18:45:59",
      "action": "BUY",
      "outcome": "YES",
      "price": 0.51,
      "price_cents": 51.0,
      "shares": 20.0,
      "cost_usd": 10.2,
      "transaction_hash": "0x9145df68a4ec6d64af7c63c47dabf2a042f7b62a11d3f40481284be3d41f2c01",
      "running_yes_shares": 40.0,
      "running_no_shares": 67.88,
      "running_yes_cost": 20.4,
      "running_no_cost": 33.94,
      "running_total_exposure": 54.34,
      "raw": {
        "proxyWallet": "0x6031b6eed1c97e853c6e0f03ad3ce3529351f96d",
        "asset": "22937902771157015749883661291284904936746607727282925886170992544903461006916",
        "conditionId": "0xf135c3d2b69fdbe31faa6ee7b6392b76921cbf1de349c9a254b671f5549e7ae8",
        "outcomeIndex": 0
      }
    },
    {
      "trade_number": 7,
      "timestamp": 1766267161,
      "datetime": "2025-12-20 18:46:01",
      "action": "BUY",
      "outcome": "YES",
      "price": 0.51,
      "price_cents": 51.0,
      "shares": 20.0,
      "cost_usd": 10.2,
      "transaction_hash": "0x024658c50c7cc59f8151ddfac42a72300b639eb426032a21383baac3f4d67c7d",
      "running_yes_shares": 60.0,
      "running_no_shares": 67.88,
      "running_yes_cost": 30.6,
      "running_no_cost": 33.94,
      "running_total_exposure": 64.54,
      "raw": {
        "proxyWallet": "0x6031b6eed1c97e853c6e0f03ad3ce3529351f96d",
        "asset": "22937902771157015749883661291284904936746607727282925886170992544903461006916",
        "conditionId": "0xf135c3d2b69fdbe31faa6ee7b6392b76921cbf1de349c9a254b671f5549e7ae8",
        "outcomeIndex": 0
      }
    },
    {
      "trade_number": 8,
      "timestamp": 1766267161,
      "datetime": "2025-12-20 18:46:01",
      "action": "BUY",
      "outcome": "YES",
      "price": 0.51,
      "price_cents": 51.0,
      "shares": 20.0,
      "cost_usd": 10.2,
      "transaction_hash": "0x89b0352d01a9f61fb3f86e82527f0d3be384519842004519a96b6a6c47367f84",
      "running_yes_shares": 80.0,
      "running_no_shares": 67.88,
      "running_yes_cost": 40.8,
      "running_no_cost": 33.94,
      "running_total_exposure": 74.74,
      "raw": {
        "proxyWallet": "0x6031b6eed1c97e853c6e0f03ad3ce3529351f96d",
        "asset": "22937902771157015749883661291284904936746607727282925886170992544903461006916",
        "conditionId": "0xf135c3d2b69fdbe31faa6ee7b6392b76921cbf1de349c9a254b671f5549e7ae8",
        "outcomeIndex": 0
      }
    },
    {
      "trade_number": 9,
      "timestamp": 1766267161,
      "datetime": "2025-12-20 18:46:01",
      "action": "BUY",
      "outcome": "YES",
      "price": 0.51,
      "price_cents": 51.0,
      "shares": 20.0,
      "cost_usd": 10.2,
      "transaction_hash": "0xb2d71f0f00f0212522b50428cffd1e80f2cc74283255ae9e65a8e9c826a48dbc",
      "running_yes_shares": 100.0,
      "running_no_shares": 67.88,
      "running_yes_cost": 51.0,
      "running_no_cost": 33.94,
      "running_total_exposure": 84.94,
      "raw": {
        "proxyWallet": "0x6031b6eed1c97e853c6e0f03ad3ce3529351f96d",
        "asset": "22937902771157015749883661291284904936746607727282925886170992544903461006916",
        "conditionId": "0xf135c3d2b69fdbe31faa6ee7b6392b76921cbf1de349c9a254b671f5549e7ae8",
        "outcomeIndex": 0
      }
    },
    {
      "trade_number": 10,
      "timestamp": 1766267161,
      "datetime": "2025-12-20 18:46:01",
      "action": "BUY",
      "outcome": "YES",
      "price": 0.51,
      "price_cents": 51.0,
      "shares": 20.0,
      "cost_usd": 10.2,
      "transaction_hash": "0x7eac5b7c2de81bd4d932648d57c3b5e29048eb68e218c6e78d761481c780e455",
      "running_yes_shares": 120.0,
      "running_no_shares": 67.88,
      "running_yes_cost": 61.2,
      "running_no_cost": 33.94,
      "running_total_exposure": 95.14,
      "raw": {
        "proxyWallet": "0x6031b6eed1c97e853c6e0f03ad3ce3529351f96d",
        "asset": "22937902771157015749883661291284904936746607727282925886170992544903461006916",
        "conditionId": "0xf135c3d2b69fdbe31faa6ee7b6392b76921cbf1de349c9a254b671f5549e7ae8",
        "outcomeIndex": 0
      }
    },
    {
      "trade_number": 11,
      "timestamp": 1766267163,
      "datetime": "2025-12-20 18:46:03",
      "action": "BUY",
      "outcome": "YES",
      "price": 0.5,
      "price_cents": 50.0,
      "shares": 4.64,
      "cost_usd": 2.32,
      "transaction_hash": "0xce86528d5192d757257b1ff851562039df1cc28af15dc4ffdba0b856656572df",
      "running_yes_shares": 124.64,
      "running_no_shares": 67.88,
      "running_yes_cost": 63.52,
      "running_no_cost": 33.94,
      "running_total_exposure": 97.46,
      "raw": {
        "proxyWallet": "0x6031b6eed1c97e853c6e0f03ad3ce3529351f96d",
        "asset": "22937902771157015749883661291284904936746607727282925886170992544903461006916",
        "conditionId": "0xf135c3d2b69fdbe31faa6ee7b6392b76921cbf1de349c9a254b671f5549e7ae8",
        "outcomeIndex": 0
      }
    },
    {
      "trade_number": 12,
      "timestamp": 1766267181,
      "datetime": "2025-12-20 18:46:21",
      "action": "BUY",
      "outcome": "YES",
      "price": 0.53,
      "price_cents": 53.0,
      "shares": 1.32,
      "cost_usd": 0.6996,
      "transaction_hash": "0x87581f123e7af415dcbfa9c6d1a5f71e1a492289da30e5690c3e7ba177b01a36",
      "running_yes_shares": 125.96,
      "running_no_shares": 67.88,
      "running_yes_cost": 64.2196,
      "running_no_cost": 33.94,
      "running_total_exposure": 98.1596,
      "raw": {
        "proxyWallet": "0x6031b6eed1c97e853c6e0f03ad3ce3529351f96d",
        "asset": "22937902771157015749883661291284904936746607727282925886170992544903461006916",
        "conditionId": "0xf135c3d2b69fdbe31faa6ee7b6392b76921cbf1de349c9a254b671f5549e7ae8",
        "outcomeIndex": 0
      }
    },
    {
      "trade_number": 13,
      "timestamp": 1766267185,
      "datetime": "2025-12-20 18:46:25",
      "action": "BUY",
      "outcome": "NO",
      "price": 0.5,
      "price_cents": 50.0,
      "shares": 18.5,
      "cost_usd": 9.25,
      "transaction_hash": "0xb864f60d7b4d0b358cf268623afede43986d04b9387d747df5b66d517f5b9aea",
      "running_yes_shares": 125.96,
      "running_no_shares": 86.38,
      "running_yes_cost": 64.2196,
      "running_no_cost": 43.19,
      "running_total_exposure": 107.4096,
      "raw": {
        "proxyWallet": "0x6031b6eed1c97e853c6e0f03ad3ce3529351f96d",
        "asset": "105393520734003569337205125847550967785785535636278335570879470805053456059467",
        "conditionId": "0xf135c3d2b69fdbe31faa6ee7b6392b76921cbf1de349c9a254b671f5549e7ae8",
        "outcomeIndex": 1
      }
    },
    {
      "trade_number": 14,
      "timestamp": 1766267187,
      "datetime": "2025-12-20 18:46:27",
      "action": "BUY",
      "outcome": "NO",
      "price": 0.61,
      "price_cents": 61.0,
      "shares": 5.0,
      "cost_usd": 3.05,
      "transaction_hash": "0xa76b8154dac4f0c450b18bd761b6b76c4b6a779911783b6fb68ca6c23ce4c122",
      "running_yes_shares": 125.96,
      "running_no_shares": 91.38,
      "running_yes_cost": 64.2196,
      "running_no_cost": 46.24,
      "running_total_exposure": 110.4596,
      "raw": {
        "proxyWallet": "0x6031b6eed1c97e853c6e0f03ad3ce3529351f96d",
        "asset": "105393520734003569337205125847550967785785535636278335570879470805053456059467",
        "conditionId": "0xf135c3d2b69fdbe31faa6ee7b6392b76921cbf1de349c9a254b671f5549e7ae8",
        "outcomeIndex": 1
      }
    },
    {
      "trade_number": 15,
      "timestamp": 1766267189,
      "datetime": "2025-12-20 18:46:29",
      "action": "BUY",
      "outcome": "NO",
      "price": 0.59,
      "price_cents": 59.0,
      "shares": 20.0,
      "cost_usd": 11.8,
      "transaction_hash": "0xe07a716dfe67df6cf58f779e635cf84eaf8ec357bbebdcfa23d9c7fd97d1ace9",
      "running_yes_shares": 125.96,
      "running_no_shares": 111.38,
      "running_yes_cost": 64.2196,
      "running_no_cost": 58.04,
      "running_total_exposure": 122.2596,
      "raw": {
        "proxyWallet": "0x6031b6eed1c97e853c6e0f03ad3ce3529351f96d",
        "asset": "105393520734003569337205125847550967785785535636278335570879470805053456059467",
        "conditionId": "0xf135c3d2b69fdbe31faa6ee7b6392b76921cbf1de349c9a254b671f5549e7ae8",
        "outcomeIndex": 1
      }
    },
    {
      "trade_number": 16,
      "timestamp": 1766267189,
      "datetime": "2025-12-20 18:46:29",
      "action": "BUY",
      "outcome": "NO",
      "price": 0.61,
      "price_cents": 61.0,
      "shares": 5.0,
      "cost_usd": 3.05,
      "transaction_hash": "0x57de2b4b5fd9e01b914be1b6977d8354385c9670fafeee8bd1e5d45c25baabb3",
      "running_yes_shares": 125.96,
      "running_no_shares": 116.38,
      "running_yes_cost": 64.2196,
      "running_no_cost": 61.09,
      "running_total_exposure": 125.3096,
      "raw": {
        "proxyWallet": "0x6031b6eed1c97e853c6e0f03ad3ce3529351f96d",
        "asset": "105393520734003569337205125847550967785785535636278335570879470805053456059467",
        "conditionId": "0xf135c3d2b69fdbe31faa6ee7b6392b76921cbf1de349c9a254b671f5549e7ae8",
        "outcomeIndex": 1
      }
    },
    {
      "trade_number": 17,
      "timestamp": 1766267191,
      "datetime": "2025-12-20 18:46:31",
      "action": "BUY",
      "outcome": "NO",
      "price": 0.64,
      "price_cents": 64.0,
      "shares": 5.0,
      "cost_usd": 3.2,
      "transaction_hash": "0x952a5dc5b249aa7d2ae4b53b7ba885a650d8745d10e308d989593265393b93f4",
      "running_yes_shares": 125.96,
      "running_no_shares": 121.38,
      "running_yes_cost": 64.2196,
      "running_no_cost": 64.29,
      "running_total_exposure": 128.5096,
      "raw": {
        "proxyWallet": "0x6031b6eed1c97e853c6e0f03ad3ce3529351f96d",
        "asset": "105393520734003569337205125847550967785785535636278335570879470805053456059467",
        "conditionId": "0xf135c3d2b69fdbe31faa6ee7b6392b76921cbf1de349c9a254b671f5549e7ae8",
        "outcomeIndex": 1
      }
    },
    {
      "trade_number": 18,
      "timestamp": 1766267191,
      "datetime": "2025-12-20 18:46:31",
      "action": "BUY",
      "outcome": "YES",
      "price": 0.35,
      "price_cents": 35.0,
      "shares": 20.0,
      "cost_usd": 7.0,
      "transaction_hash": "0x1204813f8644a411adf9cd166f281f1c6e687efe4334a6a222c3178b50f9af32",
      "running_yes_shares": 145.96,
      "running_no_shares": 121.38,
      "running_yes_cost": 71.2196,
      "running_no_cost": 64.29,
      "running_total_exposure": 135.5096,
      "raw": {
        "proxyWallet": "0x6031b6eed1c97e853c6e0f03ad3ce3529351f96d",
        "asset": "22937902771157015749883661291284904936746607727282925886170992544903461006916",
        "conditionId": "0xf135c3d2b69fdbe31faa6ee7b6392b76921cbf1de349c9a254b671f5549e7ae8",
        "outcomeIndex": 0
      }
    },
    {
      "trade_number": 19,
      "timestamp": 1766267205,
      "datetime": "2025-12-20 18:46:45",
      "action": "BUY",
      "outcome": "YES",
      "price": 0.33,
      "price_cents": 33.0,
      "shares": 20.0,
      "cost_usd": 6.6,
      "transaction_hash": "0xf8e7c9d47274432085940f934dadae4a02d81c3e293a6789b0e29f6364147441",
      "running_yes_shares": 165.96,
      "running_no_shares": 121.38,
      "running_yes_cost": 77.8196,
      "running_no_cost": 64.29,
      "running_total_exposure": 142.1096,
      "raw": {
        "proxyWallet": "0x6031b6eed1c97e853c6e0f03ad3ce3529351f96d",
        "asset": "22937902771157015749883661291284904936746607727282925886170992544903461006916",
        "conditionId": "0xf135c3d2b69fdbe31faa6ee7b6392b76921cbf1de349c9a254b671f5549e7ae8",
        "outcomeIndex": 0
      }
    },
    {
      "trade_number": 20,
      "timestamp": 1766267205,
      "datetime": "2025-12-20 18:46:45",
      "action": "BUY",
      "outcome": "YES",
      "price": 0.32,
      "price_cents": 32.0,
      "shares": 15.0,
      "cost_usd": 4.8,
      "transaction_hash": "0xce38a3f33f6d34c82824d8b107677af3c0cec7cd86ae7ebf47ed68a0529c0cef",
      "running_yes_shares": 180.96,
      "running_no_shares": 121.38,
      "running_yes_cost": 82.6196,
      "running_no_cost": 64.29,
      "running_total_exposure": 146.9096,
      "raw": {
        "proxyWallet": "0x6031b6eed1c97e853c6e0f03ad3ce3529351f96d",
        "asset": "22937902771157015749883661291284904936746607727282925886170992544903461006916",
        "conditionId": "0xf135c3d2b69fdbe31faa6ee7b6392b76921cbf1de349c9a254b671f5549e7ae8",
        "outcomeIndex": 0
      }
    },
    {
      "trade_number": 21,
      "timestamp": 1766267205,
      "datetime": "2025-12-20 18:46:45",
      "action": "BUY",
      "outcome": "YES",
      "price": 0.33,
      "price_cents": 33.0,
      "shares": 20.0,
      "cost_usd": 6.6,
      "transaction_hash": "0xae132f602d250cc25845c223127be7dc118d4f623e1d56a523da2b65ab33f2e7",
      "running_yes_shares": 200.96,
      "running_no_shares": 121.38,
      "running_yes_cost": 89.2196,
      "running_no_cost": 64.29,
      "running_total_exposure": 153.5096,
      "raw": {
        "proxyWallet": "0x6031b6eed1c97e853c6e0f03ad3ce3529351f96d",
        "asset": "22937902771157015749883661291284904936746607727282925886170992544903461006916",
        "conditionId": "0xf135c3d2b69fdbe31faa6ee7b6392b76921cbf1de349c9a254b671f5549e7ae8",
        "outcomeIndex": 0
      }
    },
    {
      "trade_number": 22,
      "timestamp": 1766267211,
      "datetime": "2025-12-20 18:46:51",
      "action": "BUY",
      "outcome": "YES",
      "price": 0.35,
      "price_cents": 35.0,
      "shares": 20.0,
      "cost_usd": 7.0,
      "transaction_hash": "0x1e13bc86e0300fd2fab856436ddee007069b8466b6ddbe15ebc448ed0be6c9a2",
      "running_yes_shares": 220.96,
      "running_no_shares": 121.38,
      "running_yes_cost": 96.2196,
      "running_no_cost": 64.29,
      "running_total_exposure": 160.5096,
      "raw": {
        "proxyWallet": "0x6031b6eed1c97e853c6e0f03ad3ce3529351f96d",
        "asset": "22937902771157015749883661291284904936746607727282925886170992544903461006916",
        "conditionId": "0xf135c3d2b69fdbe31faa6ee7b6392b76921cbf1de349c9a254b671f5549e7ae8",
        "outcomeIndex": 0
      }
    },
    {
      "trade_number": 23,
      "timestamp": 1766267211,
      "datetime": "2025-12-20 18:46:51",
      "action": "BUY",
      "outcome": "YES",
      "price": 0.36,
      "price_cents": 36.0,
      "shares": 20.0,
      "cost_usd": 7.2,
      "transaction_hash": "0x671c0a47e64af9b39a55b34ac9e6b462ee943118de30f35ee57037521f942e0c",
      "running_yes_shares": 240.96,
      "running_no_shares": 121.38,
      "running_yes_cost": 103.4196,
      "running_no_cost": 64.29,
      "running_total_exposure": 167.7096,
      "raw": {
        "proxyWallet": "0x6031b6eed1c97e853c6e0f03ad3ce3529351f96d",
        "asset": "22937902771157015749883661291284904936746607727282925886170992544903461006916",
        "conditionId": "0xf135c3d2b69fdbe31faa6ee7b6392b76921cbf1de349c9a254b671f5549e7ae8",
        "outcomeIndex": 0
      }
    },
    {
      "trade_number": 24,
      "timestamp": 1766267211,
      "datetime": "2025-12-20 18:46:51",
      "action": "BUY",
      "outcome": "NO",
      "price": 0.57,
      "price_cents": 57.0,
      "shares": 20.0,
      "cost_usd": 11.4,
      "transaction_hash": "0xff743d42025cdc8b4ca33177e1c31056d74b6566b3b5125e2a0df6fbcb5da90e",
      "running_yes_shares": 240.96,
      "running_no_shares": 141.38,
      "running_yes_cost": 103.4196,
      "running_no_cost": 75.69,
      "running_total_exposure": 179.1096,
      "raw": {
        "proxyWallet": "0x6031b6eed1c97e853c6e0f03ad3ce3529351f96d",
        "asset": "105393520734003569337205125847550967785785535636278335570879470805053456059467",
        "conditionId": "0xf135c3d2b69fdbe31faa6ee7b6392b76921cbf1de349c9a254b671f5549e7ae8",
        "outcomeIndex": 1
      }
    },
    {
      "trade_number": 25,
      "timestamp": 1766267289,
      "datetime": "2025-12-20 18:48:09",
      "action": "BUY",
      "outcome": "NO",
      "price": 0.67,
      "price_cents": 67.0,
      "shares": 5.0,
      "cost_usd": 3.35,
      "transaction_hash": "0x0892a9339e76c5847e7dd89e0a06b9ed6cfd93ccbbece3e58abc0d2452bb6520",
      "running_yes_shares": 240.96,
      "running_no_shares": 146.38,
      "running_yes_cost": 103.4196,
      "running_no_cost": 79.04,
      "running_total_exposure": 182.4596,
      "raw": {
        "proxyWallet": "0x6031b6eed1c97e853c6e0f03ad3ce3529351f96d",
        "asset": "105393520734003569337205125847550967785785535636278335570879470805053456059467",
        "conditionId": "0xf135c3d2b69fdbe31faa6ee7b6392b76921cbf1de349c9a254b671f5549e7ae8",
        "outcomeIndex": 1
      }
    },
    {
      "trade_number": 26,
      "timestamp": 1766267289,
      "datetime": "2025-12-20 18:48:09",
      "action": "BUY",
      "outcome": "NO",
      "price": 0.67,
      "price_cents": 67.0,
      "shares": 20.0,
      "cost_usd": 13.4,
      "transaction_hash": "0xe624e9ae2f243bdb00989f2a69af1cd43736584b623c4deb4510a3e458cf66aa",
      "running_yes_shares": 240.96,
      "running_no_shares": 166.38,
      "running_yes_cost": 103.4196,
      "running_no_cost": 92.44,
      "running_total_exposure": 195.8596,
      "raw": {
        "proxyWallet": "0x6031b6eed1c97e853c6e0f03ad3ce3529351f96d",
        "asset": "105393520734003569337205125847550967785785535636278335570879470805053456059467",
        "conditionId": "0xf135c3d2b69fdbe31faa6ee7b6392b76921cbf1de349c9a254b671f5549e7ae8",
        "outcomeIndex": 1
      }
    },
    {
      "trade_number": 27,
      "timestamp": 1766267289,
      "datetime": "2025-12-20 18:48:09",
      "action": "BUY",
      "outcome": "NO",
      "price": 0.67,
      "price_cents": 67.0,
      "shares": 20.0,
      "cost_usd": 13.4,
      "transaction_hash": "0x8bcdb506a9ff184970e84f7b01a0dab62a9740499739a2b59bc6a52f8fe8956e",
      "running_yes_shares": 240.96,
      "running_no_shares": 186.38,
      "running_yes_cost": 103.4196,
      "running_no_cost": 105.84,
      "running_total_exposure": 209.2596,
      "raw": {
        "proxyWallet": "0x6031b6eed1c97e853c6e0f03ad3ce3529351f96d",
        "asset": "105393520734003569337205125847550967785785535636278335570879470805053456059467",
        "conditionId": "0xf135c3d2b69fdbe31faa6ee7b6392b76921cbf1de349c9a254b671f5549e7ae8",
        "outcomeIndex": 1
      }
    },
    {
      "trade_number": 28,
      "timestamp": 1766267289,
      "datetime": "2025-12-20 18:48:09",
      "action": "BUY",
      "outcome": "YES",
      "price": 0.18,
      "price_cents": 18.0,
      "shares": 20.0,
      "cost_usd": 3.6,
      "transaction_hash": "0xf5f7a8907d85372cf65e5eb302b705aa04b12a4fdbffc779dceffa7121bf3ded",
      "running_yes_shares": 260.96,
      "running_no_shares": 186.38,
      "running_yes_cost": 107.0196,
      "running_no_cost": 105.84,
      "running_total_exposure": 212.8596,
      "raw": {
        "proxyWallet": "0x6031b6eed1c97e853c6e0f03ad3ce3529351f96d",
        "asset": "22937902771157015749883661291284904936746607727282925886170992544903461006916",
        "conditionId": "0xf135c3d2b69fdbe31faa6ee7b6392b76921cbf1de349c9a254b671f5549e7ae8",
        "outcomeIndex": 0
      }
    },
    {
      "trade_number": 29,
      "timestamp": 1766267289,
      "datetime": "2025-12-20 18:48:09",
      "action": "BUY",
      "outcome": "NO",
      "price": 0.67,
      "price_cents": 67.0,
      "shares": 20.0,
      "cost_usd": 13.4,
      "transaction_hash": "0x1c5da6f73f69652a045b39f1fc1633b380311e1d51117421f80ced38ed9dea15",
      "running_yes_shares": 260.96,
      "running_no_shares": 206.38,
      "running_yes_cost": 107.0196,
      "running_no_cost": 119.24,
      "running_total_exposure": 226.2596,
      "raw": {
        "proxyWallet": "0x6031b6eed1c97e853c6e0f03ad3ce3529351f96d",
        "asset": "105393520734003569337205125847550967785785535636278335570879470805053456059467",
        "conditionId": "0xf135c3d2b69fdbe31faa6ee7b6392b76921cbf1de349c9a254b671f5549e7ae8",
        "outcomeIndex": 1
      }
    },
    {
      "trade_number": 30,
      "timestamp": 1766267289,
      "datetime": "2025-12-20 18:48:09",
      "action": "BUY",
      "outcome": "NO",
      "price": 0.67,
      "price_cents": 67.0,
      "shares": 20.0,
      "cost_usd": 13.4,
      "transaction_hash": "0xf6767f4d9ac67c1b512ff479a1097640540d731f979d5d1f0ba8e2b3db3afcdf",
      "running_yes_shares": 260.96,
      "running_no_shares": 226.38,
      "running_yes_cost": 107.0196,
      "running_no_cost": 132.64,
      "running_total_exposure": 239.6596,
      "raw": {
        "proxyWallet": "0x6031b6eed1c97e853c6e0f03ad3ce3529351f96d",
        "asset": "105393520734003569337205125847550967785785535636278335570879470805053456059467",
        "conditionId": "0xf135c3d2b69fdbe31faa6ee7b6392b76921cbf1de349c9a254b671f5549e7ae8",
        "outcomeIndex": 1
      }
    },
    {
      "trade_number": 31,
      "timestamp": 1766267289,
      "datetime": "2025-12-20 18:48:09",
      "action": "BUY",
      "outcome": "NO",
      "price": 0.67,
      "price_cents": 67.0,
      "shares": 20.0,
      "cost_usd": 13.4,
      "transaction_hash": "0x3076794175bb8ef4a5afbae1826d60eef8941ce06a2ae086de8549911004dbe4",
      "running_yes_shares": 260.96,
      "running_no_shares": 246.38,
      "running_yes_cost": 107.0196,
      "running_no_cost": 146.04,
      "running_total_exposure": 253.0596,
      "raw": {
        "proxyWallet": "0x6031b6eed1c97e853c6e0f03ad3ce3529351f96d",
        "asset": "105393520734003569337205125847550967785785535636278335570879470805053456059467",
        "conditionId": "0xf135c3d2b69fdbe31faa6ee7b6392b76921cbf1de349c9a254b671f5549e7ae8",
        "outcomeIndex": 1
      }
    },
    {
      "trade_number": 32,
      "timestamp": 1766267289,
      "datetime": "2025-12-20 18:48:09",
      "action": "BUY",
      "outcome": "NO",
      "price": 0.67,
      "price_cents": 67.0,
      "shares": 20.0,
      "cost_usd": 13.4,
      "transaction_hash": "0xa8a96928e18dce208cf1aa4133034f93e83df206d58f152470397a4b2082b887",
      "running_yes_shares": 260.96,
      "running_no_shares": 266.38,
      "running_yes_cost": 107.0196,
      "running_no_cost": 159.44,
      "running_total_exposure": 266.4596,
      "raw": {
        "proxyWallet": "0x6031b6eed1c97e853c6e0f03ad3ce3529351f96d",
        "asset": "105393520734003569337205125847550967785785535636278335570879470805053456059467",
        "conditionId": "0xf135c3d2b69fdbe31faa6ee7b6392b76921cbf1de349c9a254b671f5549e7ae8",
        "outcomeIndex": 1
      }
    },
    {
      "trade_number": 33,
      "timestamp": 1766267289,
      "datetime": "2025-12-20 18:48:09",
      "action": "BUY",
      "outcome": "NO",
      "price": 0.67,
      "price_cents": 67.0,
      "shares": 5.0,
      "cost_usd": 3.35,
      "transaction_hash": "0xf05b39aa46bbf55ab369496baedfc79f304cc934e1ecb171ecba0f3d615b6f28",
      "running_yes_shares": 260.96,
      "running_no_shares": 271.38,
      "running_yes_cost": 107.0196,
      "running_no_cost": 162.79,
      "running_total_exposure": 269.8096,
      "raw": {
        "proxyWallet": "0x6031b6eed1c97e853c6e0f03ad3ce3529351f96d",
        "asset": "105393520734003569337205125847550967785785535636278335570879470805053456059467",
        "conditionId": "0xf135c3d2b69fdbe31faa6ee7b6392b76921cbf1de349c9a254b671f5549e7ae8",
        "outcomeIndex": 1
      }
    },
    {
      "trade_number": 34,
      "timestamp": 1766267291,
      "datetime": "2025-12-20 18:48:11",
      "action": "BUY",
      "outcome": "YES",
      "price": 0.18,
      "price_cents": 18.0,
      "shares": 20.0,
      "cost_usd": 3.6,
      "transaction_hash": "0xbce0a7a67ae8df3224992f616f4e971a39e55b1abdfbc59f73fb5887c58742d2",
      "running_yes_shares": 280.96,
      "running_no_shares": 271.38,
      "running_yes_cost": 110.6196,
      "running_no_cost": 162.79,
      "running_total_exposure": 273.4096,
      "raw": {
        "proxyWallet": "0x6031b6eed1c97e853c6e0f03ad3ce3529351f96d",
        "asset": "22937902771157015749883661291284904936746607727282925886170992544903461006916",
        "conditionId": "0xf135c3d2b69fdbe31faa6ee7b6392b76921cbf1de349c9a254b671f5549e7ae8",
        "outcomeIndex": 0
      }
    },
    {
      "trade_number": 35,
      "timestamp": 1766267291,
      "datetime": "2025-12-20 18:48:11",
      "action": "BUY",
      "outcome": "YES",
      "price": 0.18,
      "price_cents": 18.0,
      "shares": 5.0,
      "cost_usd": 0.9,
      "transaction_hash": "0x49b352738391669a290943915a390c9ad367d82f2f9188bf465d23a2cd7a63cb",
      "running_yes_shares": 285.96,
      "running_no_shares": 271.38,
      "running_yes_cost": 111.5196,
      "running_no_cost": 162.79,
      "running_total_exposure": 274.3096,
      "raw": {
        "proxyWallet": "0x6031b6eed1c97e853c6e0f03ad3ce3529351f96d",
        "asset": "22937902771157015749883661291284904936746607727282925886170992544903461006916",
        "conditionId": "0xf135c3d2b69fdbe31faa6ee7b6392b76921cbf1de349c9a254b671f5549e7ae8",
        "outcomeIndex": 0
      }
    },
    {
      "trade_number": 36,
      "timestamp": 1766267291,
      "datetime": "2025-12-20 18:48:11",
      "action": "BUY",
      "outcome": "YES",
      "price": 0.18,
      "price_cents": 18.0,
      "shares": 20.0,
      "cost_usd": 3.6,
      "transaction_hash": "0x4d0dad25c7961b52114f3d1846932dc256d26ffccd1c6ecf9d34c6d50bbe202a",
      "running_yes_shares": 305.96,
      "running_no_shares": 271.38,
      "running_yes_cost": 115.1196,
      "running_no_cost": 162.79,
      "running_total_exposure": 277.9096,
      "raw": {
        "proxyWallet": "0x6031b6eed1c97e853c6e0f03ad3ce3529351f96d",
        "asset": "22937902771157015749883661291284904936746607727282925886170992544903461006916",
        "conditionId": "0xf135c3d2b69fdbe31faa6ee7b6392b76921cbf1de349c9a254b671f5549e7ae8",
        "outcomeIndex": 0
      }
    },
    {
      "trade_number": 37,
      "timestamp": 1766267291,
      "datetime": "2025-12-20 18:48:11",
      "action": "BUY",
      "outcome": "NO",
      "price": 0.67,
      "price_cents": 67.0,
      "shares": 20.0,
      "cost_usd": 13.4,
      "transaction_hash": "0x6b2b0924b84a3f79edb2acb5d8b2d408969e69a35e519648565c22a0e19f31a6",
      "running_yes_shares": 305.96,
      "running_no_shares": 291.38,
      "running_yes_cost": 115.1196,
      "running_no_cost": 176.19,
      "running_total_exposure": 291.3096,
      "raw": {
        "proxyWallet": "0x6031b6eed1c97e853c6e0f03ad3ce3529351f96d",
        "asset": "105393520734003569337205125847550967785785535636278335570879470805053456059467",
        "conditionId": "0xf135c3d2b69fdbe31faa6ee7b6392b76921cbf1de349c9a254b671f5549e7ae8",
        "outcomeIndex": 1
      }
    },
    {
      "trade_number": 38,
      "timestamp": 1766267291,
      "datetime": "2025-12-20 18:48:11",
      "action": "BUY",
      "outcome": "YES",
      "price": 0.2,
      "price_cents": 20.0,
      "shares": 20.0,
      "cost_usd": 4.0,
      "transaction_hash": "0x163f4d8b2156e9c8e9ec3af05c3fbc6058b3466a8b93e2cda2e9da297fb0dcb6",
      "running_yes_shares": 325.96,
      "running_no_shares": 291.38,
      "running_yes_cost": 119.1196,
      "running_no_cost": 176.19,
      "running_total_exposure": 295.3096,
      "raw": {
        "proxyWallet": "0x6031b6eed1c97e853c6e0f03ad3ce3529351f96d",
        "asset": "22937902771157015749883661291284904936746607727282925886170992544903461006916",
        "conditionId": "0xf135c3d2b69fdbe31faa6ee7b6392b76921cbf1de349c9a254b671f5549e7ae8",
        "outcomeIndex": 0
      }
    },
    {
      "trade_number": 39,
      "timestamp": 1766267293,
      "datetime": "2025-12-20 18:48:13",
      "action": "BUY",
      "outcome": "YES",
      "price": 0.19,
      "price_cents": 19.0,
      "shares": 5.0,
      "cost_usd": 0.95,
      "transaction_hash": "0x3a62f6bfc9d2a61023a0d7d1ad0b70c7d3a34fa69a146c89c1eb0dbc3e1d5f7b",
      "running_yes_shares": 330.96,
      "running_no_shares": 291.38,
      "running_yes_cost": 120.0696,
      "running_no_cost": 176.19,
      "running_total_exposure": 296.2596,
      "raw": {
        "proxyWallet": "0x6031b6eed1c97e853c6e0f03ad3ce3529351f96d",
        "asset": "22937902771157015749883661291284904936746607727282925886170992544903461006916",
        "conditionId": "0xf135c3d2b69fdbe31faa6ee7b6392b76921cbf1de349c9a254b671f5549e7ae8",
        "outcomeIndex": 0
      }
    },
    {
      "trade_number": 40,
      "timestamp": 1766267293,
      "datetime": "2025-12-20 18:48:13",
      "action": "BUY",
      "outcome": "YES",
      "price": 0.11,
      "price_cents": 11.0,
      "shares": 20.0,
      "cost_usd": 2.2,
      "transaction_hash": "0x02843f9091060510af9a9a6aca1332c714ca6dba88367b412de7c616c793a978",
      "running_yes_shares": 350.96,
      "running_no_shares": 291.38,
      "running_yes_cost": 122.2696,
      "running_no_cost": 176.19,
      "running_total_exposure": 298.4596,
      "raw": {
        "proxyWallet": "0x6031b6eed1c97e853c6e0f03ad3ce3529351f96d",
        "asset": "22937902771157015749883661291284904936746607727282925886170992544903461006916",
        "conditionId": "0xf135c3d2b69fdbe31faa6ee7b6392b76921cbf1de349c9a254b671f5549e7ae8",
        "outcomeIndex": 0
      }
    },
    {
      "trade_number": 41,
      "timestamp": 1766267293,
      "datetime": "2025-12-20 18:48:13",
      "action": "BUY",
      "outcome": "YES",
      "price": 0.2,
      "price_cents": 20.0,
      "shares": 5.0,
      "cost_usd": 1.0,
      "transaction_hash": "0x9786f049cc2f00fce8bfc003e1af283b574253d26261c8520b1c1499dd2a5ea3",
      "running_yes_shares": 355.96,
      "running_no_shares": 291.38,
      "running_yes_cost": 123.2696,
      "running_no_cost": 176.19,
      "running_total_exposure": 299.4596,
      "raw": {
        "proxyWallet": "0x6031b6eed1c97e853c6e0f03ad3ce3529351f96d",
        "asset": "22937902771157015749883661291284904936746607727282925886170992544903461006916",
        "conditionId": "0xf135c3d2b69fdbe31faa6ee7b6392b76921cbf1de349c9a254b671f5549e7ae8",
        "outcomeIndex": 0
      }
    },
    {
      "trade_number": 42,
      "timestamp": 1766267293,
      "datetime": "2025-12-20 18:48:13",
      "action": "BUY",
      "outcome": "YES",
      "price": 0.2,
      "price_cents": 20.0,
      "shares": 5.0,
      "cost_usd": 1.0,
      "transaction_hash": "0x4a847cbed5c604226868c5974ea44f30ee2595be7b87bd830762478f58956e27",
      "running_yes_shares": 360.96,
      "running_no_shares": 291.38,
      "running_yes_cost": 124.2696,
      "running_no_cost": 176.19,
      "running_total_exposure": 300.4596,
      "raw": {
        "proxyWallet": "0x6031b6eed1c97e853c6e0f03ad3ce3529351f96d",
        "asset": "22937902771157015749883661291284904936746607727282925886170992544903461006916",
        "conditionId": "0xf135c3d2b69fdbe31faa6ee7b6392b76921cbf1de349c9a254b671f5549e7ae8",
        "outcomeIndex": 0
      }
    },
    {
      "trade_number": 43,
      "timestamp": 1766267321,
      "datetime": "2025-12-20 18:48:41",
      "action": "BUY",
      "outcome": "NO",
      "price": 0.83,
      "price_cents": 83.0,
      "shares": 15.0,
      "cost_usd": 12.45,
      "transaction_hash": "0x38afa0cca97eb30b259914a72aa64309b23ec8fd3c8307dc2b5cb8c1ba29845c",
      "running_yes_shares": 360.96,
      "running_no_shares": 306.38,
      "running_yes_cost": 124.2696,
      "running_no_cost": 188.64,
      "running_total_exposure": 312.9096,
      "raw": {
        "proxyWallet": "0x6031b6eed1c97e853c6e0f03ad3ce3529351f96d",
        "asset": "105393520734003569337205125847550967785785535636278335570879470805053456059467",
        "conditionId": "0xf135c3d2b69fdbe31faa6ee7b6392b76921cbf1de349c9a254b671f5549e7ae8",
        "outcomeIndex": 1
      }
    },
    {
      "trade_number": 44,
      "timestamp": 1766267349,
      "datetime": "2025-12-20 18:49:09",
      "action": "BUY",
      "outcome": "YES",
      "price": 0.17,
      "price_cents": 17.0,
      "shares": 20.0,
      "cost_usd": 3.4,
      "transaction_hash": "0xb2123d8b0ba692fdcc11e0505a299a54da995cc38a7d837bd8040b1487fc0b14",
      "running_yes_shares": 380.96,
      "running_no_shares": 306.38,
      "running_yes_cost": 127.6696,
      "running_no_cost": 188.64,
      "running_total_exposure": 316.3096,
      "raw": {
        "proxyWallet": "0x6031b6eed1c97e853c6e0f03ad3ce3529351f96d",
        "asset": "22937902771157015749883661291284904936746607727282925886170992544903461006916",
        "conditionId": "0xf135c3d2b69fdbe31faa6ee7b6392b76921cbf1de349c9a254b671f5549e7ae8",
        "outcomeIndex": 0
      }
    },
    {
      "trade_number": 45,
      "timestamp": 1766267349,
      "datetime": "2025-12-20 18:49:09",
      "action": "BUY",
      "outcome": "YES",
      "price": 0.17,
      "price_cents": 17.0,
      "shares": 20.0,
      "cost_usd": 3.4,
      "transaction_hash": "0x1d646d1f9477cc65ee54fd593a67f24c157519c2a886af3f7b0145ae1a6b5574",
      "running_yes_shares": 400.96,
      "running_no_shares": 306.38,
      "running_yes_cost": 131.0696,
      "running_no_cost": 188.64,
      "running_total_exposure": 319.7096,
      "raw": {
        "proxyWallet": "0x6031b6eed1c97e853c6e0f03ad3ce3529351f96d",
        "asset": "22937902771157015749883661291284904936746607727282925886170992544903461006916",
        "conditionId": "0xf135c3d2b69fdbe31faa6ee7b6392b76921cbf1de349c9a254b671f5549e7ae8",
        "outcomeIndex": 0
      }
    },
    {
      "trade_number": 46,
      "timestamp": 1766267407,
      "datetime": "2025-12-20 18:50:07",
      "action": "BUY",
      "outcome": "NO",
      "price": 0.85,
      "price_cents": 85.0,
      "shares": 10.0,
      "cost_usd": 8.5,
      "transaction_hash": "0x5ee868f0ce4106233551f0f1c28a9a9b34957666d15c3876a8896645e2f17872",
      "running_yes_shares": 400.96,
      "running_no_shares": 316.38,
      "running_yes_cost": 131.0696,
      "running_no_cost": 197.14,
      "running_total_exposure": 328.2096,
      "raw": {
        "proxyWallet": "0x6031b6eed1c97e853c6e0f03ad3ce3529351f96d",
        "asset": "105393520734003569337205125847550967785785535636278335570879470805053456059467",
        "conditionId": "0xf135c3d2b69fdbe31faa6ee7b6392b76921cbf1de349c9a254b671f5549e7ae8",
        "outcomeIndex": 1
      }
    }
  ]
}